Workbook

Sheet Dashboard
A1: Gulf Startup & University Advisor Outreach Database – Madhiyazhagan
A2: UAE (Dubai focus) • Saudi Arabia • Oman • Kuwait • Bahrain | Curated for external advisor / mentor outreach | 26 Sep 2026
A4: Database KPI | B4: Value | D4: Outreach Readiness | E4: Value
A5: Total targets | B5: =COUNTA('Master Mail List'!A2:A66) -> 65 | D5: Named contact + email | E5: =COUNTIF('Master Mail List'!U2:U66,"Named contact + public email") -> 17
A6: Countries | B6: 5 | D6: Functional / program email | E6: =COUNTIF('Master Mail List'!U2:U66,"Functional / program email") -> 37
A7: Primary-email targets | B7: =COUNTA('Master Mail List'!K2:K66) -> 54 | D7: Official route – no email | E7: =COUNTIF('Master Mail List'!U2:U66,"Official route – no public email verified") -> 11
A8: Priority A | B8: =COUNTIF('Master Mail List'!P2:P66,"A") -> 45 | D8: Drafted | E8: =COUNTIF('Master Mail List'!W2:W66,"Drafted") -> 0
A9: Engineering / Tech Universities | B9: =COUNTIF('Master Mail List'!E2:E66,"Engineering / Technology University") -> 15 | D9: Sent | E9: =COUNTIF('Master Mail List'!W2:W66,"Sent") -> 32
A10: B-School / University Entrepreneurship | B10: =COUNTIF('Master Mail List'!E2:E66,"B-School / University Entrepreneurship") -> 14 | D10: Meetings | E10: =COUNTIF('Master Mail List'!W2:W66,"Meeting Booked") -> 0
A11: Accelerators / Incubators | B11: =COUNTIF('Master Mail List'!E2:E66,"Accelerator / Incubator") -> 21
A12: Government / Startup Ecosystem | B12: =COUNTIF('Master Mail List'!E2:E66,"Government / Startup Ecosystem") -> 15
A15: Country | B15: Targets | D15: Country | E15: Total | F15: With Email
A16: UAE | B16: =COUNTIF('Master Mail List'!B2:B66,A16) -> 19 | D16: UAE | E16: =COUNTIF('Master Mail List'!B2:B66,D16) -> 19 | F16: =COUNTIFS('Master Mail List'!B2:B66,D16,'Master Mail List'!K2:K66,"<>") -> 15
A17: Saudi Arabia | B17: =COUNTIF('Master Mail List'!B2:B66,A17) -> 16 | D17: Saudi Arabia | E17: =COUNTIF('Master Mail List'!B2:B66,D17) -> 16 | F17: =COUNTIFS('Master Mail List'!B2:B66,D17,'Master Mail List'!K2:K66,"<>") -> 13
A18: Oman | B18: =COUNTIF('Master Mail List'!B2:B66,A18) -> 11 | D18: Oman | E18: =COUNTIF('Master Mail List'!B2:B66,D18) -> 11 | F18: =COUNTIFS('Master Mail List'!B2:B66,D18,'Master Mail List'!K2:K66,"<>") -> 11
A19: Kuwait | B19: =COUNTIF('Master Mail List'!B2:B66,A19) -> 8 | D19: Kuwait | E19: =COUNTIF('Master Mail List'!B2:B66,D19) -> 8 | F19: =COUNTIFS('Master Mail List'!B2:B66,D19,'Master Mail List'!K2:K66,"<>") -> 7
A20: Bahrain | B20: =COUNTIF('Master Mail List'!B2:B66,A20) -> 11 | D20: Bahrain | E20: =COUNTIF('Master Mail List'!B2:B66,D20) -> 11 | F20: =COUNTIFS('Master Mail List'!B2:B66,D20,'Master Mail List'!K2:K66,"<>") -> 8

Sheet Master Mail List
A1: ID | B1: Country | C1: Region / Emirate / Province | D1: City | E1: Category | F1: Institution / Organisation | G1: Incubator / Program / Unit | H1: Organisation Profile / Relevance | I1: Contact Name | J1: Contact Role | K1: Primary Email | L1: CC / Alternate Email | M1: Phone | N1: Contact / Profile URL | O1: Official Source URL | P1: Priority | Q1: Why Madhiyazhagan Fits | R1: Suggested Subject | S1: Personalization Hook | T1: Best Entry Route | U1: Contact Quality | V1: Verified On | W1: Email Status | X1: Last Contacted | Y1: Notes
A2: 1 | B2: UAE | C2: Abu Dhabi | D2: Abu Dhabi | E2: Accelerator / Incubator | F2: Hub71 | G2: Hub71 startup ecosystem | H2: Abu Dhabi global tech ecosystem offering startup programs, market access, investor and corporate connections. | I2: Hub71 Team | J2: Ecosystem / startup team | K2: info@hub71.com | M2: +971 2 449 1515 | N2: https://www.hub71.com/ | O2: https://www.hub71.com/contact | P2: A | Q2: Cohort mentoring, AI/product strategy, enterprise GTM, founder reviews and Germany/Europe–GCC market access. | R2: External Advisor / Mentor – AI, Product & Germany–GCC | Hub71 startup ecosystem | S2: I came across Hub71 startup ecosystem at Hub71 and its work around abu dhabi global tech ecosystem offering startup programs, market access, investor and corporate connections. | T2: Use the program/functional email with a concise external mentor/advisor proposition. | U2: Functional / program email | V2: 46291 | W2: Already contacted | Y2: Already emailed in earlier batch (same address)
A3: 2 | B3: UAE | C3: Abu Dhabi | D3: Abu Dhabi | E3: Accelerator / Incubator | F3: startAD – NYU Abu Dhabi | G3: startAD | H3: NYU Abu Dhabi-based accelerator and innovation platform connecting startups, corporates, investors and mentors. | I3: Ashwin Joshi | J3: Director, startAD | K3: startAD@nyu.edu | N3: https://startad.ae/ | O3: https://startad.ae/contact/ | P3: A | Q3: Cohort mentoring, AI/product strategy, enterprise GTM, founder reviews and Germany/Europe–GCC market access. | R3: External Advisor / Mentor – AI, Product & Germany–GCC | startAD | S3: I came across startAD at startAD – NYU Abu Dhabi and its work around nyu abu dhabi-based accelerator and innovation platform connecting startups, corporates, investors and mentors. | T3: Write directly to the named contact using the public email and ask about contributing to the mentor/advisor network. | U3: Named contact + public email | V3: 46291 | W3: Already contacted | Y3: Already emailed in earlier batch (same address)
A4: 3 | B4: UAE | C4: Dubai | D4: Dubai | E4: Accelerator / Incubator | F4: Dubai Technology Entrepreneur Campus (Dtec) | G4: Dtec | H4: Dubai Silicon Oasis technology startup hub offering incubation, workspace, market access and ecosystem support. | I4: Dtec Team | J4: Startup / ecosystem team | K4: dtec.sales@dtec.ae | L4: community@dtec.ae | M4: +971 4 501 5000 | N4: https://dtec.ae/ | O4: https://dtec.ae/contact/ | P4: A | Q4: Cohort mentoring, AI/product strategy, enterprise GTM, founder reviews and Germany/Europe–GCC market access. | R4: External Advisor / Mentor – AI, Product & Germany–GCC | Dtec | S4: I came across Dtec at Dubai Technology Entrepreneur Campus (Dtec) and its work around dubai silicon oasis technology startup hub offering incubation, workspace, market access and ecosystem support. | T4: Use the program/functional email with a concise external mentor/advisor proposition. | U4: Functional / program email | V4: 46291 | W4: Skipped | Y4: Dtec already emailed (dtec@dso.ae)
A5: 4 | B5: UAE | C5: Dubai | D5: Dubai | E5: Government / Startup Ecosystem | F5: Mohammed Bin Rashid Innovation Fund (MBRIF) | G5: Innovation Accelerator | H5: UAE Ministry of Finance initiative supporting innovative companies through acceleration and growth services. | I5: MBRIF Team | J5: Innovation / accelerator team | K5: contact@mbrif.ae | L5: info@mbrinnovationfund.ae | N5: https://mbrif.ae/ | O5: https://mbrif.ae/ar/contact-us-2/ | P5: A | Q5: Founder capacity building, AI adoption, mentor programs, ecosystem partnerships and Germany/Europe–GCC market connections. | R5: External Mentor / Advisor Support | Innovation Accelerator | S5: I came across Innovation Accelerator at Mohammed Bin Rashid Innovation Fund (MBRIF) and its work around uae ministry of finance initiative supporting innovative companies through acceleration and growth services. | T5: Use the program/functional email with a concise external mentor/advisor proposition. | U5: Functional / program email | V5: 46291 | W5: Sent | X5: 46291 | Y5: Position around founder mentoring, enterprise readiness and international expansion.
A6: 5 | B6: UAE | C6: Sharjah | D6: Sharjah | E6: Accelerator / Incubator | F6: Sharjah Entrepreneurship Center (Sheraa) | G6: Sheraa | H6: Sharjah startup ecosystem builder supporting founders through programs, incubation, mentorship and market access. | I6: Sara Abdelaziz Al Nuaimi | J6: CEO | K6: info@sheraa.ae | M6: +971 6 558 5000 | N6: https://sheraa.ae/about-us | O6: https://sheraa.ae/contact-us | P6: A | Q6: Cohort mentoring, AI/product strategy, enterprise GTM, founder reviews and Germany/Europe–GCC market access. | R6: External Advisor / Mentor – AI, Product & Germany–GCC | Sheraa | S6: I came across Sheraa at Sharjah Entrepreneurship Center (Sheraa) and its work around sharjah startup ecosystem builder supporting founders through programs, incubation, mentorship and market access. | T6: Write directly to the named contact using the public email and ask about contributing to the mentor/advisor network. | U6: Named contact + public email | V6: 46291 | W6: Already contacted | Y6: Already emailed in earlier batch (same address)
A7: 6 | B7: UAE | C7: Dubai | D7: Dubai | E7: Accelerator / Incubator | F7: DIFC Innovation Hub | G7: Innovation Hub | H7: Dubai International Financial Centre innovation ecosystem for fintech, AI, digital assets and venture growth. | I7: Mohammad Alblooshi | J7: Chief Executive Officer | N7: https://www.innovationhub.difc.ae/the-hub/about-innovation-hub | O7: https://www.innovationhub.difc.ae/ | P7: B | Q7: Cohort mentoring, AI/product strategy, enterprise GTM, founder reviews and Germany/Europe–GCC market access. | R7: External Advisor / Mentor – AI, Product & Germany–GCC | Innovation Hub | S7: I came across Innovation Hub at DIFC Innovation Hub and its work around dubai international financial centre innovation ecosystem for fintech, ai, digital assets and venture growth. | T7: Use the official contact/partnership route and ask to be connected to the mentor, partnerships or incubation lead. | U7: Official route – no public email verified | V7: 46291 | W7: Skipped | Y7: No email in database
A8: 7 | B8: UAE | C8: Dubai | D8: Dubai | E8: Government / Startup Ecosystem | F8: Dubai Future Foundation | G8: Future ecosystem / innovation programs | H8: Dubai government innovation platform running future technology, startup and ecosystem initiatives. | I8: Dubai Future Foundation Team | J8: Partnership / innovation team | M8: +971 4 516 6565 | N8: https://www.dubaifuture.ae/ | O8: https://www.dubaifuture.ae/reach-us/ | P8: B | Q8: Founder capacity building, AI adoption, mentor programs, ecosystem partnerships and Germany/Europe–GCC market connections. | R8: External Mentor / Advisor Support | Future ecosystem / innovation programs | S8: I came across Future ecosystem / innovation programs at Dubai Future Foundation and its work around dubai government innovation platform running future technology, startup and ecosystem initiatives. | T8: Use the official contact/partnership route and ask to be connected to the mentor, partnerships or incubation lead. | U8: Official route – no public email verified | V8: 46291 | W8: Skipped | Y8: No email in database
A9: 8 | B9: UAE | C9: Dubai | D9: Dubai | E9: Government / Startup Ecosystem | F9: Dubai Chamber of Digital Economy | G9: Digital Economy ecosystem | H9: Dubai Chambers entity supporting digital companies, startups, market entry and ecosystem development. | I9: Digital Economy Team | J9: Customer / ecosystem team | K9: customercare@dubaichamber.com | M9: 800 CHAMBER (242 6237) | N9: https://www.dubaichamber.com/ | O9: https://myhub.dubaichamber.com/en/web/dubai-chamber-of-digital-economy/home | P9: A | Q9: Founder capacity building, AI adoption, mentor programs, ecosystem partnerships and Germany/Europe–GCC market connections. | R9: External Mentor / Advisor Support | Digital Economy ecosystem | S9: I came across Digital Economy ecosystem at Dubai Chamber of Digital Economy and its work around dubai chambers entity supporting digital companies, startups, market entry and ecosystem development. | T9: Use the program/functional email with a concise external mentor/advisor proposition. | U9: Functional / program email | V9: 46291 | W9: Skipped | Y9: Only a customer care inbox
A10: 9 | B10: UAE | C10: Abu Dhabi | D10: Abu Dhabi | E10: Government / Startup Ecosystem | F10: Khalifa Fund for Enterprise Development | G10: Entrepreneurship support | H10: Abu Dhabi government entity supporting entrepreneurship, SME development, capability building and market access. | I10: Khalifa Fund Team | J10: Entrepreneurship support team | K10: info@khalifafund.ae | M10: +971 2 696 0000 | N10: https://www.khalifafund.ae/ | O10: https://www.khalifafund.ae/contact/ | P10: A | Q10: Founder capacity building, AI adoption, mentor programs, ecosystem partnerships and Germany/Europe–GCC market connections. | R10: External Mentor / Advisor Support | Entrepreneurship support | S10: I came across Entrepreneurship support at Khalifa Fund for Enterprise Development and its work around abu dhabi government entity supporting entrepreneurship, sme development, capability building and market access. | T10: Use the program/functional email with a concise external mentor/advisor proposition. | U10: Functional / program email | V10: 46291 | W10: Sent | X10: 46291 | Y10: Offer founder mentoring, AI adoption and Germany/Europe connections.
A11: 10 | B11: UAE | C11: Sharjah | D11: Sharjah | E11: Government / Startup Ecosystem | F11: Sharjah SME – RUWAD | G11: Entrepreneurship support | H11: Sharjah government SME development body supporting entrepreneurs through advisory, training and business support. | I11: RUWAD Team | J11: SME / entrepreneurship team | K11: info@ruwad.ae | L11: cs@ruwad.ae | M11: +971 6 512 2555 | N11: https://www.ruwad.ae/ | O11: https://www.ruwad.ae/ | P11: A | Q11: Founder capacity building, AI adoption, mentor programs, ecosystem partnerships and Germany/Europe–GCC market connections. | R11: External Mentor / Advisor Support | Entrepreneurship support | S11: I came across Entrepreneurship support at Sharjah SME – RUWAD and its work around sharjah government sme development body supporting entrepreneurs through advisory, training and business support. | T11: Use the program/functional email with a concise external mentor/advisor proposition. | U11: Functional / program email | V11: 46291 | W11: Sent | X11: 46291 | Y11: Good route for mentor/advisor contribution to SME founders.
A12: 11 | B12: UAE | C12: Dubai | D12: Dubai | E12: B-School / University Entrepreneurship | F12: University of Dubai | G12: Innovation, Entrepreneurship & Business Centre (IEBC) | H12: University entrepreneurship centre offering pitch competitions, workshops, mentoring, incubation and ecosystem connections. | I12: IEBC Team | J12: Entrepreneurship & incubation team | K12: Info.iebc@ud.ac.ae | L12: startup.support@ud.ac.ae | M12: +971 4 556 6800 | N12: https://ud.ac.ae/entrepreneurship-and-business-centre-udiebc/ | O12: https://ud.ac.ae/entrepreneurship-and-business-centre-udiebc/ | P12: A | Q12: Startup mentoring, business models, GTM, enterprise readiness, entrepreneurship education and Germany–GCC connections. | R12: External Advisor / Mentor – AI, Product & Germany–GCC | University of Dubai | S12: I came across Innovation, Entrepreneurship & Business Centre (IEBC) at University of Dubai and its work around university entrepreneurship centre offering pitch competitions, workshops, mentoring, incubation and ecosystem connections. | T12: Use the program/functional email with a concise external mentor/advisor proposition. | U12: Functional / program email | V12: 46291 | W12: Already contacted | Y12: Already emailed in earlier batch (same address)
A13: 12 | B13: UAE | C13: Abu Dhabi | D13: Abu Dhabi | E13: Engineering / Technology University | F13: Khalifa University | G13: Technology Management & Innovation | H13: University office responsible for research commercialization, startups, licensing and industry engagement. | I13: Aysha Ali Rashed AlNuaimi | J13: Acting Director, Technology Management & Innovation | K13: aysha.alnuaimi@ku.ac.ae | L13: ip@ku.ac.ae | N13: https://www.ku.ac.ae/research-offices/technology-management-innovation/our-team | O13: https://www.ku.ac.ae/research-offices/technology-management-innovation | P13: A | Q13: AI/product strategy, enterprise technology, research commercialization, founder mentoring and Germany–GCC market connections. | R13: External Advisor / Mentor – AI, Product & Germany–GCC | Technology Management & Innovation | S13: I came across Technology Management & Innovation at Khalifa University and its work around university office responsible for research commercialization, startups, licensing and industry engagement. | T13: Write directly to the named contact using the public email and ask about contributing to the mentor/advisor network. | U13: Named contact + public email | V13: 46291 | W13: Sent | X13: 46291 | Y13: Direct named decision-maker and strong commercialization fit.
A14: 13 | B14: UAE | C14: Abu Dhabi | D14: Abu Dhabi | E14: Engineering / Technology University | F14: Mohamed bin Zayed University of Artificial Intelligence (MBZUAI) | G14: Incubation & Entrepreneurship Center (IEC) | H14: AI university incubation center helping founders build and scale AI startups, with mentor and ecosystem partner networks. | I14: IEC Team | J14: Incubation & Entrepreneurship Center | K14: iec@mbzuai.ac.ae | L14: info@mbzuai.ac.ae | M14: +971 2 811 3333 | N14: https://mbzuai.ac.ae/innovation-partnerships/incubation-entrepreneurship-center | O14: https://mbzuai.ac.ae/about-us/contact-mbzuai | P14: A | Q14: AI/product strategy, enterprise technology, research commercialization, founder mentoring and Germany–GCC market connections. | R14: External Advisor / Mentor – AI, Product & Germany–GCC | Mohamed bin Zayed University of Artificial Intelligence (MBZUAI) | S14: I came across Incubation & Entrepreneurship Center (IEC) at Mohamed bin Zayed University of Artificial Intelligence (MBZUAI) and its work around ai university incubation center helping founders build and scale ai startups, with mentor and ecosystem partner networks. | T14: Use the program/functional email with a concise external mentor/advisor proposition. | U14: Functional / program email | V14: 46291 | W14: Sent | X14: 46291 | Y14: Very strong AI/startup mentoring alignment.
A15: 14 | B15: UAE | C15: Sharjah | D15: Sharjah | E15: Engineering / Technology University | F15: University of Sharjah | G15: Innovation Hub | H15: University innovation hub supporting entrepreneurship, technology development and commercialization. | I15: Engr. Mahmoud Abu Shammeh | J15: Director, Innovation Hub | K15: abushammeh@sharjah.ac.ae | L15: mmadi@sharjah.ac.ae | N15: https://www.sharjah.ac.ae/en/Services/Departments/Innovation-Hub | O15: https://www.sharjah.ac.ae/en/Services/Departments/Innovation-Hub | P15: A | Q15: AI/product strategy, enterprise technology, research commercialization, founder mentoring and Germany–GCC market connections. | R15: External Advisor / Mentor – AI, Product & Germany–GCC | Innovation Hub | S15: I came across Innovation Hub at University of Sharjah and its work around university innovation hub supporting entrepreneurship, technology development and commercialization. | T15: Write directly to the named contact using the public email and ask about contributing to the mentor/advisor network. | U15: Named contact + public email | V15: 46291 | W15: Sent | X15: 46291 | Y15: Named director; strong innovation/commercialization target.
A16: 15 | B16: UAE | C16: Abu Dhabi | D16: Al Ain | E16: B-School / University Entrepreneurship | F16: United Arab Emirates University (UAEU) | G16: Emirates Centre for Entrepreneurship Research | H16: University entrepreneurship research ecosystem linking entrepreneurship, education, research and enterprise development. | I16: Dr. Ishara Maharaj | J16: Entrepreneurship research contact | K16: ishara.maharaj@uaeu.ac.ae | L16: savagepd@uaeu.ac.ae | N16: https://www.uaeu.ac.ae/en/research/ | O16: https://www.uaeu.ac.ae/en/research/research-booklet-uaeu-2024.pdf | P16: B | Q16: Startup mentoring, business models, GTM, enterprise readiness, entrepreneurship education and Germany–GCC connections. | R16: External Advisor / Mentor – AI, Product & Germany–GCC | United Arab Emirates University (UAEU) | S16: I came across Emirates Centre for Entrepreneurship Research at United Arab Emirates University (UAEU) and its work around university entrepreneurship research ecosystem linking entrepreneurship, education, research and enterprise development. | T16: Write directly to the named contact using the public email and ask about contributing to the mentor/advisor network. | U16: Named contact + public email | V16: 46291 | W16: Sent | X16: 46291 | Y16: Good for entrepreneurship teaching, research and mentor collaboration.
A17: 16 | B17: UAE | C17: Dubai | D17: Dubai | E17: Engineering / Technology University | F17: Rochester Institute of Technology Dubai (RIT Dubai) | G17: Projects & Development / entrepreneurship ecosystem | H17: Technology-focused Dubai campus with industry projects and entrepreneurship-oriented activities. | I17: Yousef Al Mannaee | J17: Projects & Development Manager | K17: yaacad@rit.edu | L17: dubai@rit.edu | M17: +971 4 371 2000 | N17: https://www.rit.edu/dubai/directory | O17: https://www.rit.edu/dubai/ | P17: A | Q17: AI/product strategy, enterprise technology, research commercialization, founder mentoring and Germany–GCC market connections. | R17: External Advisor / Mentor – AI, Product & Germany–GCC | Rochester Institute of Technology Dubai (RIT Dubai) | S17: I came across Projects & Development / entrepreneurship ecosystem at Rochester Institute of Technology Dubai (RIT Dubai) and its work around technology-focused dubai campus with industry projects and entrepreneurship-oriented activities. | T17: Write directly to the named contact using the public email and ask about contributing to the mentor/advisor network. | U17: Named contact + public email | V17: 46291 | W17: Sent | X17: 46291 | Y17: Direct contact plus technology and industry-project fit.
A18: 17 | B18: UAE | C18: Dubai | D18: Dubai | E18: B-School / University Entrepreneurship | F18: SP Jain School of Global Management | G18: Dubai Campus | H18: Global business school with Dubai campus and entrepreneurship/business programs. | I18: Amol Sawant | J18: Dubai campus contact | K18: amol.sawant@spjain.org | L18: admissions.dxb@spjain.org | N18: https://www.spjain.org/global-campus/dubai | O18: https://www.spjain.ae/contact-us | P18: B | Q18: Startup mentoring, business models, GTM, enterprise readiness, entrepreneurship education and Germany–GCC connections. | R18: External Advisor / Mentor – AI, Product & Germany–GCC | Dubai Campus | S18: I came across Dubai Campus at SP Jain School of Global Management and its work around global business school with dubai campus and entrepreneurship/business programs. | T18: Write directly to the named contact using the public email and ask about contributing to the mentor/advisor network. | U18: Named contact + public email | V18: 46291 | W18: Sent | X18: 46291 | Y18: Pitch mentor/guest advisor role around AI, product, startup execution and Europe connections.
A19: 18 | B19: UAE | C19: Dubai / Abu Dhabi | D19: Dubai | E19: B-School / University Entrepreneurship | F19: Zayed University | G19: Innovation & Entrepreneurship Center | H19: University center supporting innovation, entrepreneurship education and engagement with ecosystem partners. | I19: Innovation & Entrepreneurship Center Team | J19: University entrepreneurship team | N19: https://www.zu.ac.ae/main/en/ie-center/index | O19: https://www.zu.ac.ae/main/en/ie-center/index | P19: B | Q19: Startup mentoring, business models, GTM, enterprise readiness, entrepreneurship education and Germany–GCC connections. | R19: External Advisor / Mentor – AI, Product & Germany–GCC | Innovation & Entrepreneurship Center | S19: I came across Innovation & Entrepreneurship Center at Zayed University and its work around university center supporting innovation, entrepreneurship education and engagement with ecosystem partners. | T19: Use the official contact/partnership route and ask to be connected to the mentor, partnerships or incubation lead. | U19: Official route – no public email verified | V19: 46291 | W19: Skipped | Y19: No email in database
A20: 19 | B20: UAE | C20: Sharjah | D20: Sharjah | E20: B-School / University Entrepreneurship | F20: American University of Sharjah | G20: Department of Management, Strategy & Entrepreneurship | H20: Business-school department covering entrepreneurship, strategy and management with industry-facing academic activity. | I20: Dr. Virginia Bodolica | J20: Department leadership | N20: https://www.aus.edu/sba/department-of-management-strategy-entrepreneurship | O20: https://www.aus.edu/sba/department-of-management-strategy-entrepreneurship | P20: C | Q20: Startup mentoring, business models, GTM, enterprise readiness, entrepreneurship education and Germany–GCC connections. | R20: External Advisor / Mentor – AI, Product & Germany–GCC | American University of Sharjah | S20: I came across Department of Management, Strategy & Entrepreneurship at American University of Sharjah and its work around business-school department covering entrepreneurship, strategy and management with industry-facing academic activity. | T20: Use the official contact/partnership route and ask to be connected to the mentor, partnerships or incubation lead. | U20: Official route – no public email verified | V20: 46291 | W20: Skipped | Y20: No email in database
A21: 20 | B21: Saudi Arabia | C21: Riyadh | D21: Riyadh | E21: Government / Startup Ecosystem | F21: Monsha'at – Small and Medium Enterprises General Authority | G21: Innovation Center | H21: Saudi government innovation centers supporting technology startups through incubation, consultations, workshops and expert guidance. | I21: Monsha'at Innovation Center Team | J21: Innovation Center | K21: InnovationCenters@monshaat.gov.sa | L21: Info@monshaat.gov.sa | M21: 8003018888 | N21: https://www.monshaat.gov.sa/en/innovation_center | O21: https://www.monshaat.gov.sa/en/support | P21: A | Q21: Founder capacity building, AI adoption, mentor programs, ecosystem partnerships and Germany/Europe–GCC market connections. | R21: External Mentor / Advisor Support | Innovation Center | S21: I came across Innovation Center at Monsha'at – Small and Medium Enterprises General Authority and its work around saudi government innovation centers supporting technology startups through incubation, consultations, workshops and expert guidance. | T21: Use the program/functional email with a concise external mentor/advisor proposition. | U21: Functional / program email | V21: 46291 | W21: Sent | X21: 46291 | Y21: Explicit expert consultations make this a strong external-mentor target.
A22: 21 | B22: Saudi Arabia | C22: Riyadh | D22: Riyadh | E22: Government / Startup Ecosystem | F22: Ministry of Communications and Information Technology (MCIT) | G22: CODE Gate | H22: Government technology entrepreneurship platform supporting digital startups and innovation programs. | I22: CODE / MCIT Team | J22: Technology entrepreneurship team | K22: info@mcit.gov.sa | M22: 011 814 4444 | N22: https://code.mcit.gov.sa/ | O22: https://my.gov.sa/en/services/2477063 | P22: A | Q22: Founder capacity building, AI adoption, mentor programs, ecosystem partnerships and Germany/Europe–GCC market connections. | R22: External Mentor / Advisor Support | CODE Gate | S22: I came across CODE Gate at Ministry of Communications and Information Technology (MCIT) and its work around government technology entrepreneurship platform supporting digital startups and innovation programs. | T22: Use the program/functional email with a concise external mentor/advisor proposition. | U22: Functional / program email | V22: 46291 | W22: Skipped | Y22: Only a general ministry inbox
A23: 22 | B23: Saudi Arabia | C23: Riyadh | D23: Riyadh | E23: Government / Startup Ecosystem | F23: Ministry of Communications and Information Technology (MCIT) | G23: Tech Founders | H23: MCIT technology entrepreneurship program supporting startup founders and technology venture development. | I23: Tech Founders Team | J23: Technology entrepreneurship program | K23: info@mcit.gov.sa | M23: 011 814 4444 | N23: https://www.mcit.gov.sa/ | O23: https://my.gov.sa/en/services/2422923 | P23: B | Q23: Founder capacity building, AI adoption, mentor programs, ecosystem partnerships and Germany/Europe–GCC market connections. | R23: External Mentor / Advisor Support | Tech Founders | S23: I came across Tech Founders at Ministry of Communications and Information Technology (MCIT) and its work around mcit technology entrepreneurship program supporting startup founders and technology venture development. | T23: Use the program/functional email with a concise external mentor/advisor proposition. | U23: Functional / program email | V23: 46291 | W23: Skipped | Y23: Only a general ministry inbox
A24: 23 | B24: Saudi Arabia | C24: Riyadh | D24: Riyadh | E24: Accelerator / Incubator | F24: Mohammed bin Salman Foundation (Misk) | G24: Misk Entrepreneurship | H24: Entrepreneurship programs supporting young founders, venture development and ecosystem connections. | I24: Misk Entrepreneurship Team | J24: Entrepreneurship team | K24: contact@misk.org.sa | N24: https://misk.org.sa/en/ | O24: https://misk.org.sa/en/ask-misk-en/ | P24: A | Q24: Cohort mentoring, AI/product strategy, enterprise GTM, founder reviews and Germany/Europe–GCC market access. | R24: External Advisor / Mentor – AI, Product & Germany–GCC | Misk Entrepreneurship | S24: I came across Misk Entrepreneurship at Mohammed bin Salman Foundation (Misk) and its work around entrepreneurship programs supporting young founders, venture development and ecosystem connections. | T24: Use the program/functional email with a concise external mentor/advisor proposition. | U24: Functional / program email | V24: 46291 | W24: Sent | X24: 46291 | Y24: Pitch practical founder mentoring and international-market sessions.
A25: 24 | B25: Saudi Arabia | C25: Makkah Province | D25: Thuwal | E25: Engineering / Technology University | F25: King Abdullah University of Science and Technology (KAUST) | G25: Entrepreneurship Center | H25: KAUST entrepreneurship ecosystem supporting technology founders, startup training and acceleration. | I25: KAUST Entrepreneurship Team | J25: Entrepreneurship Center | K25: leap@kaust.edu.sa | L25: entrepreneurship@kaust.edu.sa | N25: https://leap.kaust.edu.sa/entrepreneurship-center.html | O25: https://www.kaust.edu.sa/ | P25: A | Q25: AI/product strategy, enterprise technology, research commercialization, founder mentoring and Germany–GCC market connections. | R25: External Advisor / Mentor – AI, Product & Germany–GCC | Entrepreneurship Center | S25: I came across Entrepreneurship Center at King Abdullah University of Science and Technology (KAUST) and its work around kaust entrepreneurship ecosystem supporting technology founders, startup training and acceleration. | T25: Use the program/functional email with a concise external mentor/advisor proposition. | U25: Functional / program email | V25: 46291 | W25: Sent | X25: 46291 | Y25: Deep-tech commercialization and international-market fit.
A26: 25 | B26: Saudi Arabia | C26: Makkah Province | D26: Thuwal | E26: Accelerator / Incubator | F26: KAUST | G26: TAQADAM Accelerator | H26: KAUST startup accelerator supporting early-stage ventures with mentoring, training and ecosystem access. | I26: TAQADAM Team | J26: Accelerator team | K26: Apply.Taqadam@kaust.edu.sa | N26: https://taqadam.kaust.edu.sa/ | O26: https://taqadam.kaust.edu.sa/ | P26: A | Q26: Cohort mentoring, AI/product strategy, enterprise GTM, founder reviews and Germany/Europe–GCC market access. | R26: External Advisor / Mentor – AI, Product & Germany–GCC | TAQADAM Accelerator | S26: I came across TAQADAM Accelerator at KAUST and its work around kaust startup accelerator supporting early-stage ventures with mentoring, training and ecosystem access. | T26: Use the program/functional email with a concise external mentor/advisor proposition. | U26: Functional / program email | V26: 46291 | W26: Skipped | Y26: KAUST covered via Entrepreneurship Center email
A27: 26 | B27: Saudi Arabia | C27: Makkah Province | D27: Thuwal | E27: Accelerator / Incubator | F27: KAUST | G27: KAUST Innovation Fund | H27: University-linked venture fund investing in technology startups and spin-ins, including international ventures establishing activity in Saudi Arabia. | I27: KAUST Innovation Fund Team | J27: Innovation Fund | K27: KIF@kaust.edu.sa | L27: entrepreneurship@kaust.edu.sa | N27: https://www.kaust.edu.sa/ | O27: https://www.kaust.edu.sa/en/news/how-kaust-is-enabling-the-in-kingdom-entrepreneurs-of-tomorrow | P27: A | Q27: Cohort mentoring, AI/product strategy, enterprise GTM, founder reviews and Germany/Europe–GCC market access. | R27: External Advisor / Mentor – AI, Product & Germany–GCC | KAUST Innovation Fund | S27: I came across KAUST Innovation Fund at KAUST and its work around university-linked venture fund investing in technology startups and spin-ins, including international ventures establishing activity in saudi arabia. | T27: Use the program/functional email with a concise external mentor/advisor proposition. | U27: Functional / program email | V27: 46291 | W27: Skipped | Y27: KAUST covered via Entrepreneurship Center email
A28: 27 | B28: Saudi Arabia | C28: Riyadh | D28: Riyadh | E28: B-School / University Entrepreneurship | F28: King Saud University | G28: Entrepreneurship Institute | H28: University entrepreneurship institute supporting innovation, entrepreneurial education and venture development. | I28: Dr. Khalid Alhussaini | J28: Executive Director, Entrepreneurship Institute | K28: kalhussaini@ksu.edu.sa | L28: fmalessa@ksu.edu.sa | M28: 011 806 2212 | N28: https://ei.ksu.edu.sa/en/workteam_En | O28: https://ei.ksu.edu.sa/en/workteam_En | P28: A | Q28: Startup mentoring, business models, GTM, enterprise readiness, entrepreneurship education and Germany–GCC connections. | R28: External Advisor / Mentor – AI, Product & Germany–GCC | Entrepreneurship Institute | S28: I came across Entrepreneurship Institute at King Saud University and its work around university entrepreneurship institute supporting innovation, entrepreneurial education and venture development. | T28: Write directly to the named contact using the public email and ask about contributing to the mentor/advisor network. | U28: Named contact + public email | V28: 46291 | W28: Sent | X28: 46291 | Y28: Direct named leadership.
A29: 28 | B29: Saudi Arabia | C29: Makkah Province | D29: Jeddah | E29: Engineering / Technology University | F29: King Abdulaziz University | G29: Center for Innovation & Entrepreneurship | H29: University center supporting innovation, startup creation and entrepreneurship. | I29: Center for Innovation & Entrepreneurship Team | J29: Center team | K29: iec@kau.edu.sa | N29: https://kau.edu.sa/en/page/center-for-innovation-and-entrepreneurship | O29: https://kau.edu.sa/en/page/center-for-innovation-and-entrepreneurship | P29: A | Q29: AI/product strategy, enterprise technology, research commercialization, founder mentoring and Germany–GCC market connections. | R29: External Advisor / Mentor – AI, Product & Germany–GCC | Center for Innovation & Entrepreneurship | S29: I came across Center for Innovation & Entrepreneurship at King Abdulaziz University and its work around university center supporting innovation, startup creation and entrepreneurship. | T29: Use the program/functional email with a concise external mentor/advisor proposition. | U29: Functional / program email | V29: 46291 | W29: Already contacted | Y29: Already emailed in earlier batch (same address)
A30: 29 | B30: Saudi Arabia | C30: Eastern Province | D30: Dhahran | E30: Engineering / Technology University | F30: King Fahd University of Petroleum & Minerals (KFUPM) | G30: Entrepreneurship Institute | H30: Technology university entrepreneurship ecosystem supporting innovation and startup development. | I30: Prof. Wail A. Mousa | J30: Entrepreneurship / faculty contact | K30: wailmousa@kfupm.edu.sa | N30: https://faculty.kfupm.edu.sa/EE/wailmousa/ | O30: https://www.kfupm.edu.sa/ | P30: B | Q30: AI/product strategy, enterprise technology, research commercialization, founder mentoring and Germany–GCC market connections. | R30: External Advisor / Mentor – AI, Product & Germany–GCC | Entrepreneurship Institute | S30: I came across Entrepreneurship Institute at King Fahd University of Petroleum & Minerals (KFUPM) and its work around technology university entrepreneurship ecosystem supporting innovation and startup development. | T30: Write directly to the named contact using the public email and ask about contributing to the mentor/advisor network. | U30: Named contact + public email | V30: 46291 | W30: Skipped | Y30: KFUPM already emailed (ei@kfupm.edu.sa)
A31: 30 | B31: Saudi Arabia | C31: Riyadh | D31: Riyadh | E31: B-School / University Entrepreneurship | F31: Alfaisal University | G31: Center for Innovation, Partnership & Community Engagement (CIPC) | H31: University center connecting innovation, partnerships, entrepreneurship and community/industry engagement. | I31: CIPC Team | J31: Innovation & partnerships team | K31: cipc@alfaisal.edu | M31: +966 11 215 7792 | N31: https://cipc.alfaisal.edu/ | O31: https://cipc.alfaisal.edu/contact-us | P31: A | Q31: Startup mentoring, business models, GTM, enterprise readiness, entrepreneurship education and Germany–GCC connections. | R31: External Advisor / Mentor – AI, Product & Germany–GCC | Alfaisal University | S31: I came across Center for Innovation, Partnership & Community Engagement (CIPC) at Alfaisal University and its work around university center connecting innovation, partnerships, entrepreneurship and community/industry engagement. | T31: Use the program/functional email with a concise external mentor/advisor proposition. | U31: Functional / program email | V31: 46291 | W31: Skipped | Y31: Alfaisal covered via Accelerator email (CIPC in cc)
A32: 31 | B32: Saudi Arabia | C32: Riyadh | D32: Riyadh | E32: Accelerator / Incubator | F32: Alfaisal University | G32: Alfaisal Accelerator | H32: University accelerator supporting venture development and entrepreneurship. | I32: Alfaisal Accelerator Team | J32: Accelerator team | K32: center@alfaisal.edu | M32: +966 11 215 7967 | N32: https://center.alfaisal.edu/accelerator | O32: https://center.alfaisal.edu/accelerator | P32: A | Q32: Cohort mentoring, AI/product strategy, enterprise GTM, founder reviews and Germany/Europe–GCC market access. | R32: External Advisor / Mentor – AI, Product & Germany–GCC | Alfaisal Accelerator | S32: I came across Alfaisal Accelerator at Alfaisal University and its work around university accelerator supporting venture development and entrepreneurship. | T32: Use the program/functional email with a concise external mentor/advisor proposition. | U32: Functional / program email | V32: 46291 | W32: Sent | X32: 46291 | Y32: Direct accelerator route.
A33: 32 | B33: Saudi Arabia | C33: Makkah Province | D33: Jeddah | E33: B-School / University Entrepreneurship | F33: Effat University | G33: Business Innovation & Entrepreneurship Research Center | H33: University research center focused on business innovation and entrepreneurship. | I33: Center Team | J33: Business innovation / entrepreneurship center | N33: https://www.effatuniversity.edu.sa/English/Research/Research-Centers/Business-Innovation-and-Entrepreneurship/Pages/default.aspx | O33: https://www.effatuniversity.edu.sa/English/Research/Research-Centers/Business-Innovation-and-Entrepreneurship/Pages/default.aspx | P33: B | Q33: Startup mentoring, business models, GTM, enterprise readiness, entrepreneurship education and Germany–GCC connections. | R33: External Advisor / Mentor – AI, Product & Germany–GCC | Effat University | S33: I came across Business Innovation & Entrepreneurship Research Center at Effat University and its work around university research center focused on business innovation and entrepreneurship. | T33: Use the official contact/partnership route and ask to be connected to the mentor, partnerships or incubation lead. | U33: Official route – no public email verified | V33: 46291 | W33: Skipped | Y33: No email in database
A34: 33 | B34: Saudi Arabia | C34: Riyadh | D34: Riyadh | E34: B-School / University Entrepreneurship | F34: Prince Sultan University | G34: Entrepreneurship Club | H34: University entrepreneurship community offering student/founder activities and business exposure. | I34: Entrepreneurship Club Team | J34: Entrepreneurship community | K34: epclub@psu.edu.sa | N34: https://www.psu.edu.sa/en/resources | O34: https://www.psu.edu.sa/en/resources | P34: C | Q34: Startup mentoring, business models, GTM, enterprise readiness, entrepreneurship education and Germany–GCC connections. | R34: External Advisor / Mentor – AI, Product & Germany–GCC | Entrepreneurship Club | S34: I came across Entrepreneurship Club at Prince Sultan University and its work around university entrepreneurship community offering student/founder activities and business exposure. | T34: Use the program/functional email with a concise external mentor/advisor proposition. | U34: Functional / program email | V34: 46291 | W34: Sent | X34: 46291 | Y34: Student-facing route; use for workshops/guest mentoring rather than formal board ask.
A35: 34 | B35: Saudi Arabia | C35: Riyadh | D35: Riyadh | E35: Accelerator / Incubator | F35: stc | G35: inspireU | H35: Corporate accelerator supporting digital/technology startups with business support, mentoring and market opportunities. | I35: inspireU Team | J35: Corporate accelerator | N35: https://www.stc.com/en/inspire-u/apply-now.html | O35: https://www.stc.com/en/inspire-u/apply-now.html | P35: B | Q35: Cohort mentoring, AI/product strategy, enterprise GTM, founder reviews and Germany/Europe–GCC market access. | R35: External Advisor / Mentor – AI, Product & Germany–GCC | inspireU | S35: I came across inspireU at stc and its work around corporate accelerator supporting digital/technology startups with business support, mentoring and market opportunities. | T35: Use the official contact/partnership route and ask to be connected to the mentor, partnerships or incubation lead. | U35: Official route – no public email verified | V35: 46291 | W35: Skipped | Y35: No email in database
A36: 35 | B36: Saudi Arabia | C36: Riyadh | D36: Riyadh | E36: Accelerator / Incubator | F36: The Garage | G36: Startup / deep-tech innovation hub | H36: Riyadh startup hub supporting technology founders, accelerators, venture programs and innovation community activity. | I36: The Garage Team | J36: Startup ecosystem team | N36: https://thegarage.sa/ | O36: https://erp.thegarage.sa/contactus | P36: B | Q36: Cohort mentoring, AI/product strategy, enterprise GTM, founder reviews and Germany/Europe–GCC market access. | R36: External Advisor / Mentor – AI, Product & Germany–GCC | Startup / deep-tech innovation hub | S36: I came across Startup / deep-tech innovation hub at The Garage and its work around riyadh startup hub supporting technology founders, accelerators, venture programs and innovation community activity. | T36: Use the official contact/partnership route and ask to be connected to the mentor, partnerships or incubation lead. | U36: Official route – no public email verified | V36: 46291 | W36: Skipped | Y36: No email in database
A37: 36 | B37: Oman | C37: Muscat | D37: Muscat | E37: Government / Startup Ecosystem | F37: Small and Medium Enterprises Development Authority (Riyada) | G37: SME & entrepreneurship ecosystem | H37: Oman government authority supporting SMEs, entrepreneurs, incubators and entrepreneurship programs. | I37: H.E. Halima Al-Zari | J37: Chairperson | K37: Doc@sme.gov.om | L37: support_dpt@sme.gov.om | M37: +968 2202 2222 | N37: https://sme.gov.om/en/ | O37: https://sme.gov.om/en/contact-us/ | P37: A | Q37: Founder capacity building, AI adoption, mentor programs, ecosystem partnerships and Germany/Europe–GCC market connections. | R37: External Mentor / Advisor Support | SME & entrepreneurship ecosystem | S37: I came across SME & entrepreneurship ecosystem at Small and Medium Enterprises Development Authority (Riyada) and its work around oman government authority supporting smes, entrepreneurs, incubators and entrepreneurship programs. | T37: Write directly to the named contact using the public email and ask about contributing to the mentor/advisor network. | U37: Named contact + public email | V37: 46291 | W37: Sent | X37: 46291 | Y37: Government-level ecosystem target; use concise partnership/mentor proposition.
A38: 37 | B38: Oman | C38: Muscat | D38: Muscat | E38: Government / Startup Ecosystem | F38: ITHCA Group | G38: Technology investment & innovation ecosystem | H38: Oman technology investment group supporting ICT, innovation, digital businesses and national technology development. | I38: ITHCA Team | J38: Innovation / investment ecosystem | K38: info@ithca.om | M38: +968 2231 0500 | N38: https://ithca.om/ | O38: https://ithca.om/contact/ | P38: A | Q38: Founder capacity building, AI adoption, mentor programs, ecosystem partnerships and Germany/Europe–GCC market connections. | R38: External Mentor / Advisor Support | ITHCA Group | S38: I came across Technology investment & innovation ecosystem at ITHCA Group and its work around oman technology investment group supporting ict, innovation, digital businesses and national technology development. | T38: Use the program/functional email with a concise external mentor/advisor proposition. | U38: Functional / program email | V38: 46291 | W38: Sent | X38: 46291 | Y38: Strong enterprise-tech and international ecosystem fit.
A39: 38 | B39: Oman | C39: Muscat | D39: Muscat | E39: Accelerator / Incubator | F39: Oman Technology Fund (OTF) | G39: Technology investment / acceleration | H39: Technology investment platform supporting innovative technology ventures and ecosystem development. | I39: OTF Team | J39: Investment / accelerator team | K39: info@otf.om | M39: +968 2417 2717 | N39: https://www.otf.om/ | O39: https://www.otf.om/__trashed-3/contact/ | P39: A | Q39: Cohort mentoring, AI/product strategy, enterprise GTM, founder reviews and Germany/Europe–GCC market access. | R39: External Advisor / Mentor – AI, Product & Germany–GCC | Technology investment / acceleration | S39: I came across Technology investment / acceleration at Oman Technology Fund (OTF) and its work around technology investment platform supporting innovative technology ventures and ecosystem development. | T39: Use the program/functional email with a concise external mentor/advisor proposition. | U39: Functional / program email | V39: 46291 | W39: Sent | X39: 46291 | Y39: Pitch startup reviews, AI/product mentoring and international-market support.
A40: 39 | B40: Oman | C40: Muscat | D40: Muscat | E40: Government / Startup Ecosystem | F40: Oman Startup Hub | G40: National startup ecosystem platform | H40: Digital startup ecosystem platform connecting founders, advisors, investors and support organizations in Oman. | I40: Oman Startup Hub Team | J40: Startup ecosystem team | K40: support@omanstartuphub.om | N40: https://omanstartuphub.om/ | O40: https://omanstartuphub.om/contact-us | P40: A | Q40: Founder capacity building, AI adoption, mentor programs, ecosystem partnerships and Germany/Europe–GCC market connections. | R40: External Mentor / Advisor Support | National startup ecosystem platform | S40: I came across National startup ecosystem platform at Oman Startup Hub and its work around digital startup ecosystem platform connecting founders, advisors, investors and support organizations in oman. | T40: Use the program/functional email with a concise external mentor/advisor proposition. | U40: Functional / program email | V40: 46291 | W40: Sent | X40: 46291 | Y40: Advisor network makes this directly aligned with your objective.
A41: 40 | B41: Oman | C41: Muscat | D41: Muscat | E41: Engineering / Technology University | F41: Sultan Qaboos University | G41: Innovation & Technology Transfer Centre | H41: University innovation center covering incubation, mentoring, industry links, licensing, accelerators and entrepreneurship development. | I41: Dr. Adil Said Ali Al-Busaidi | J41: Director, Innovation & Technology Transfer Centre | K41: abusaid@squ.edu.om | L41: innovation@squ.edu.om | M41: +968 2414 6125 | N41: https://www.squ.edu.om/rc/Innovation-Technology-Transfer/About-the-Center | O41: https://innovation.squ.edu.om/contact-us | P41: A | Q41: AI/product strategy, enterprise technology, research commercialization, founder mentoring and Germany–GCC market connections. | R41: External Advisor / Mentor – AI, Product & Germany–GCC | Innovation & Technology Transfer Centre | S41: I came across Innovation & Technology Transfer Centre at Sultan Qaboos University and its work around university innovation center covering incubation, mentoring, industry links, licensing, accelerators and entrepreneurship development. | T41: Write directly to the named contact using the public email and ask about contributing to the mentor/advisor network. | U41: Named contact + public email | V41: 46291 | W41: Sent | X41: 46291 | Y41: Excellent direct named contact and strong advisor fit.
A42: 41 | B42: Oman | C42: Muscat | D42: Muscat | E42: Accelerator / Incubator | F42: Middle East College | G42: MEC Incubation Centre | H42: University incubation center supporting student and startup entrepreneurship. | I42: Incubation Centre Contact | J42: Incubation centre | K42: ralhatmi@mec.edu.om | N42: https://mec.edu.om/en/mec-incubation-centre/ | O42: https://mec.edu.om/en/mec-incubation-centre/ | P42: A | Q42: Cohort mentoring, AI/product strategy, enterprise GTM, founder reviews and Germany/Europe–GCC market access. | R42: External Advisor / Mentor – AI, Product & Germany–GCC | MEC Incubation Centre | S42: I came across MEC Incubation Centre at Middle East College and its work around university incubation center supporting student and startup entrepreneurship. | T42: Use the program/functional email with a concise external mentor/advisor proposition. | U42: Functional / program email | V42: 46291 | W42: Sent | X42: 46291 | Y42: Good mentor/workshop target.
A43: 42 | B43: Oman | C43: Al Batinah North | D43: Sohar | E43: Engineering / Technology University | F43: Sohar University | G43: Technology Transfer & Incubation Centre | H43: University center supporting technology transfer, commercialization, entrepreneurship and incubation. | I43: Tameema Al-Hinai | J43: Technology Transfer & Incubation Centre | K43: thinai@su.edu.om | L43: FSHshibli@su.edu.om | N43: https://www.su.edu.om/knowledge-transfer-and-incubation-centre/ | O43: https://www.su.edu.om/knowledge-transfer-and-incubation-centre/ | P43: A | Q43: AI/product strategy, enterprise technology, research commercialization, founder mentoring and Germany–GCC market connections. | R43: External Advisor / Mentor – AI, Product & Germany–GCC | Technology Transfer & Incubation Centre | S43: I came across Technology Transfer & Incubation Centre at Sohar University and its work around university center supporting technology transfer, commercialization, entrepreneurship and incubation. | T43: Write directly to the named contact using the public email and ask about contributing to the mentor/advisor network. | U43: Named contact + public email | V43: 46291 | W43: Sent | X43: 46291 | Y43: Direct contact; good commercialization and mentoring angle.
A44: 43 | B44: Oman | C44: Muscat | D44: Muscat | E44: Engineering / Technology University | F44: National University of Science & Technology | G44: Incubation Centre – Money Factory | H44: University incubation initiative focused on innovation, entrepreneurship and venture development. | I44: Ibrahim Issa Al Balushi | J44: Head, Incubation Centre | K44: info@nu.edu.om | N44: https://nu.edu.om/research/research-incubation-centers/ | O44: https://nu.edu.om/research/research-incubation-centers/ | P44: B | Q44: AI/product strategy, enterprise technology, research commercialization, founder mentoring and Germany–GCC market connections. | R44: External Advisor / Mentor – AI, Product & Germany–GCC | Incubation Centre – Money Factory | S44: I came across Incubation Centre – Money Factory at National University of Science & Technology and its work around university incubation initiative focused on innovation, entrepreneurship and venture development. | T44: Write directly to the named contact using the public email and ask about contributing to the mentor/advisor network. | U44: Named contact + public email | V44: 46291 | W44: Skipped | Y44: NU Oman already emailed; only general info@ inbox
A45: 44 | B45: Oman | C45: Muscat | D45: Muscat | E45: B-School / University Entrepreneurship | F45: College of Banking and Financial Studies | G45: Innovation & entrepreneurship ecosystem | H45: Oman higher-education institution focused on business, banking, finance and professional development, with innovation/entrepreneurship activity. | I45: CBFS Team | J45: Innovation / business education | K45: info@cbfs.edu.om | M45: +968 2452 8888 | N45: https://cbfs.edu.om/ | O45: https://cbfs.edu.om/contact-us/ | P45: B | Q45: Startup mentoring, business models, GTM, enterprise readiness, entrepreneurship education and Germany–GCC connections. | R45: External Advisor / Mentor – AI, Product & Germany–GCC | Innovation & entrepreneurship ecosystem | S45: I came across Innovation & entrepreneurship ecosystem at College of Banking and Financial Studies and its work around oman higher-education institution focused on business, banking, finance and professional development, with innovation/entrepreneurship activity. | T45: Use the program/functional email with a concise external mentor/advisor proposition. | U45: Functional / program email | V45: 46291 | W45: Skipped | Y45: Only a general college info inbox
A46: 45 | B46: Oman | C46: Muscat | D46: Muscat | E46: B-School / University Entrepreneurship | F46: Muscat University | G46: Business & entrepreneurship ecosystem | H46: Private university with business, logistics and technology programs and industry engagement. | I46: Muscat University Team | J46: University / business programs | K46: info@muscatuniversity.edu.om | L46: study@muscatuniversity.edu.om | N46: https://muscatuniversity.edu.om/ | O46: https://muscatuniversity.edu.om/contact-us/ | P46: B | Q46: Startup mentoring, business models, GTM, enterprise readiness, entrepreneurship education and Germany–GCC connections. | R46: External Advisor / Mentor – AI, Product & Germany–GCC | Business & entrepreneurship ecosystem | S46: I came across Business & entrepreneurship ecosystem at Muscat University and its work around private university with business, logistics and technology programs and industry engagement. | T46: Use the program/functional email with a concise external mentor/advisor proposition. | U46: Functional / program email | V46: 46291 | W46: Skipped | Y46: Only general university info/admissions inboxes
A47: 46 | B47: Oman | C47: Ash Sharqiyah South | D47: Sur | E47: Engineering / Technology University | F47: University of Technology and Applied Sciences (UTAS) – Sur | G47: Entrepreneurship / applied technology ecosystem | H47: Applied-technology university branch with entrepreneurship and industry-facing academic activity. | I47: UTAS Sur Team | J47: University / entrepreneurship route | K47: pro.sur@utas.edu.om | N47: https://www.utas.edu.om/sur/ | O47: https://www.utas.edu.om/sur/ | P47: C | Q47: AI/product strategy, enterprise technology, research commercialization, founder mentoring and Germany–GCC market connections. | R47: External Advisor / Mentor – AI, Product & Germany–GCC | University of Technology and Applied Sciences (UTAS) – Sur | S47: I came across Entrepreneurship / applied technology ecosystem at University of Technology and Applied Sciences (UTAS) – Sur and its work around applied-technology university branch with entrepreneurship and industry-facing academic activity. | T47: Use the program/functional email with a concise external mentor/advisor proposition. | U47: Functional / program email | V47: 46291 | W47: Skipped | Y47: Only a public relations inbox
A48: 47 | B48: Kuwait | C48: Al Asimah | D48: Kuwait City | E48: Government / Startup Ecosystem | F48: National Fund for SME Development | G48: SME support, incubation & accelerator ecosystem | H48: Kuwait government fund supporting SMEs through training, incubators, innovation centers, accelerators and support services. | I48: National Fund Team | J48: SME / entrepreneurship support | K48: Info@nationalfund.gov.kw | M48: 136 | N48: https://www.nationalfund.gov.kw/en/ | O48: https://www.nationalfund.gov.kw/en/about-us/our-services/support-services-center/ | P48: A | Q48: Founder capacity building, AI adoption, mentor programs, ecosystem partnerships and Germany/Europe–GCC market connections. | R48: External Mentor / Advisor Support | National Fund for SME Development | S48: I came across SME support, incubation & accelerator ecosystem at National Fund for SME Development and its work around kuwait government fund supporting smes through training, incubators, innovation centers, accelerators and support services. | T48: Use the program/functional email with a concise external mentor/advisor proposition. | U48: Functional / program email | V48: 46291 | W48: Sent | X48: 46291 | Y48: Top government ecosystem target.
A49: 48 | B49: Kuwait | C49: Al Asimah | D49: Kuwait City | E49: Engineering / Technology University | F49: Kuwait University | G49: Department of Institutional Innovation / Kuwait University Innovation Zone | H49: University innovation platform supporting institutional innovation and entrepreneurship activities. | I49: KUIZ Team | J49: Institutional innovation | K49: kuiz@ku.edu.kw | M49: 24982858 / 24983448 | N49: https://kuiz.ku.edu.kw/ | O49: https://kuiz.ku.edu.kw/contact-us | P49: A | Q49: AI/product strategy, enterprise technology, research commercialization, founder mentoring and Germany–GCC market connections. | R49: External Advisor / Mentor – AI, Product & Germany–GCC | Kuwait University | S49: I came across Department of Institutional Innovation / Kuwait University Innovation Zone at Kuwait University and its work around university innovation platform supporting institutional innovation and entrepreneurship activities. | T49: Use the program/functional email with a concise external mentor/advisor proposition. | U49: Functional / program email | V49: 46291 | W49: Sent | X49: 46291 | Y49: Strong university innovation route.
A50: 49 | B50: Kuwait | C50: Hawalli | D50: Mubarak Al-Abdullah | E50: B-School / University Entrepreneurship | F50: Gulf University for Science and Technology (GUST) | G50: Startup Lab | H50: University startup lab supporting entrepreneurship, innovation and student venture activity. | I50: GUST Startup Lab Team | J50: Startup / entrepreneurship lab | N50: https://www.gust.edu.kw/sdg/sdg9 | O50: https://www.gust.edu.kw/sdg/sdg4/4-3/4-3-1 | P50: B | Q50: Startup mentoring, business models, GTM, enterprise readiness, entrepreneurship education and Germany–GCC connections. | R50: External Advisor / Mentor – AI, Product & Germany–GCC | Startup Lab | S50: I came across Startup Lab at Gulf University for Science and Technology (GUST) and its work around university startup lab supporting entrepreneurship, innovation and student venture activity. | T50: Use the official contact/partnership route and ask to be connected to the mentor, partnerships or incubation lead. | U50: Official route – no public email verified | V50: 46291 | W50: Skipped | Y50: No email in database
A51: 50 | B51: Kuwait | C51: Al Ahmadi | D51: Egaila | E51: B-School / University Entrepreneurship | F51: American University of the Middle East (AUM) | G51: AI & Entrepreneurship / MBA ecosystem | H51: University offering entrepreneurship and AI-focused executive/academic programs and business education. | I51: AUM Team | J51: AI / entrepreneurship program | K51: info@aum.edu.kw | L51: MBA.admissions@aum.edu.kw | M51: +965 2225 1400 | N51: https://www.aum.edu.kw/ | O51: https://www.aum.edu.kw/english/about-aum/international-relations/aum---uc-berkeley-certification-program-in-ai-and-entrepreneurship | P51: B | Q51: Startup mentoring, business models, GTM, enterprise readiness, entrepreneurship education and Germany–GCC connections. | R51: External Advisor / Mentor – AI, Product & Germany–GCC | AI & Entrepreneurship / MBA ecosystem | S51: I came across AI & Entrepreneurship / MBA ecosystem at American University of the Middle East (AUM) and its work around university offering entrepreneurship and ai-focused executive/academic programs and business education. | T51: Use the program/functional email with a concise external mentor/advisor proposition. | U51: Functional / program email | V51: 46291 | W51: Skipped | Y51: Only general info/admissions inboxes
A52: 51 | B52: Kuwait | C52: Al Asimah | D52: Salmiya | E52: B-School / University Entrepreneurship | F52: American University of Kuwait (AUK) | G52: College of Business & Economics | H52: Business school with entrepreneurship, innovation and management teaching/research. | I52: Dr. Naeimah Alkharafi | J52: Entrepreneurship / business faculty | K52: nalkharafi@auk.edu.kw | L52: cbe@auk.edu.kw | N52: https://www.auk.edu.kw/academics/college-of-business-economics | O52: https://www.auk.edu.kw/academics/college-of-business-economics | P52: A | Q52: Startup mentoring, business models, GTM, enterprise readiness, entrepreneurship education and Germany–GCC connections. | R52: External Advisor / Mentor – AI, Product & Germany–GCC | College of Business & Economics | S52: I came across College of Business & Economics at American University of Kuwait (AUK) and its work around business school with entrepreneurship, innovation and management teaching/research. | T52: Write directly to the named contact using the public email and ask about contributing to the mentor/advisor network. | U52: Named contact + public email | V52: 46291 | W52: Sent | X52: 46291 | Y52: Named faculty route; good mentor/guest speaker entry.
A53: 52 | B53: Kuwait | C53: Al Asimah | D53: Kuwait City | E53: Accelerator / Incubator | F53: Sirdab Lab | G53: Startup accelerator / entrepreneurship community | H53: Kuwait entrepreneurship platform providing startup programs, training and ecosystem support. | I53: Sirdab Lab Team | J53: Startup programs | K53: info@sirdab-lab.com | M53: +965 9776 8939 | N53: https://sirdab-lab.com/ | O53: https://sirdab-lab.com/ | P53: A | Q53: Cohort mentoring, AI/product strategy, enterprise GTM, founder reviews and Germany/Europe–GCC market access. | R53: External Advisor / Mentor – AI, Product & Germany–GCC | Sirdab Lab | S53: I came across Startup accelerator / entrepreneurship community at Sirdab Lab and its work around kuwait entrepreneurship platform providing startup programs, training and ecosystem support. | T53: Use the program/functional email with a concise external mentor/advisor proposition. | U53: Functional / program email | V53: 46291 | W53: Already contacted | Y53: Already emailed in earlier batch (same address)
A54: 53 | B54: Kuwait | C54: Al Asimah | D54: Kuwait City | E54: Accelerator / Incubator | F54: Kuwait Innovation Center | G54: Innovation Center | H54: Innovation platform supporting entrepreneurship, innovation programs and business development. | I54: Mohammad AlRefaei | J54: Chief Executive Officer | K54: info@kinncenter.com | M54: +965 9409 0194 | N54: https://www.kinncenter.com/ | O54: https://www.kinncenter.com/contactus | P54: A | Q54: Cohort mentoring, AI/product strategy, enterprise GTM, founder reviews and Germany/Europe–GCC market access. | R54: External Advisor / Mentor – AI, Product & Germany–GCC | Innovation Center | S54: I came across Innovation Center at Kuwait Innovation Center and its work around innovation platform supporting entrepreneurship, innovation programs and business development. | T54: Write directly to the named contact using the public email and ask about contributing to the mentor/advisor network. | U54: Named contact + public email | V54: 46291 | W54: Sent | X54: 46291 | Y54: Named CEO with functional email.
A55: 54 | B55: Kuwait | C55: Al Asimah | D55: Kuwait City | E55: Government / Startup Ecosystem | F55: Kuwait Foundation for the Advancement of Sciences (KFAS) | G55: Innovation & Enterprise | H55: National science and innovation foundation supporting enterprise innovation and commercialization programs. | I55: Innovation & Enterprise Team | J55: Enterprise support | K55: enterprisesupport@kfas.org.kw | N55: https://www.kfas.org/ | O55: https://app.kfas.org.kw/coFunding%20Support%20Form/Form1.aspx | P55: A | Q55: Founder capacity building, AI adoption, mentor programs, ecosystem partnerships and Germany/Europe–GCC market connections. | R55: External Mentor / Advisor Support | Innovation & Enterprise | S55: I came across Innovation & Enterprise at Kuwait Foundation for the Advancement of Sciences (KFAS) and its work around national science and innovation foundation supporting enterprise innovation and commercialization programs. | T55: Use the program/functional email with a concise external mentor/advisor proposition. | U55: Functional / program email | V55: 46291 | W55: Sent | X55: 46291 | Y55: Strong innovation/commercialization and corporate ecosystem target.
A56: 55 | B56: Bahrain | C56: Capital Governorate | D56: Manama | E56: Government / Startup Ecosystem | F56: Tamkeen – Labour Fund | G56: Entrepreneurship & enterprise support | H56: Bahrain public-sector institution supporting enterprise growth, skills, entrepreneurship and business development. | I56: Tamkeen Team | J56: Enterprise support | K56: support@tamkeen.bh | L56: info@tamkeen.bh | M56: +973 1738 3333 | N56: https://www.tamkeen.bh/ | O56: https://www.tamkeen.bh/ | P56: A | Q56: Founder capacity building, AI adoption, mentor programs, ecosystem partnerships and Germany/Europe–GCC market connections. | R56: External Mentor / Advisor Support | Entrepreneurship & enterprise support | S56: I came across Entrepreneurship & enterprise support at Tamkeen – Labour Fund and its work around bahrain public-sector institution supporting enterprise growth, skills, entrepreneurship and business development. | T56: Use the program/functional email with a concise external mentor/advisor proposition. | U56: Functional / program email | V56: 46291 | W56: Sent | X56: 46291 | Y56: Top public ecosystem route; pitch mentor capacity building and international connections.
A57: 56 | B57: Bahrain | C57: Capital Governorate | D57: Manama | E57: Government / Startup Ecosystem | F57: Bahrain Economic Development Board (Bahrain EDB) | G57: Investment & innovation ecosystem | H57: Bahrain investment promotion agency supporting companies, market entry and stakeholder introductions across growth sectors. | I57: Bahrain EDB Team | J57: Investment / ecosystem team | K57: hello@bahrainedb.com | M57: +973 1758 9999 | N57: https://www.bahrainedb.com/ | O57: https://www.bahrainedb.com/contact-us | P57: A | Q57: Founder capacity building, AI adoption, mentor programs, ecosystem partnerships and Germany/Europe–GCC market connections. | R57: External Mentor / Advisor Support | Investment & innovation ecosystem | S57: I came across Investment & innovation ecosystem at Bahrain Economic Development Board (Bahrain EDB) and its work around bahrain investment promotion agency supporting companies, market entry and stakeholder introductions across growth sectors. | T57: Use the program/functional email with a concise external mentor/advisor proposition. | U57: Functional / program email | V57: 46291 | W57: Sent | X57: 46291 | Y57: Berlin/Germany base creates a strong international ecosystem angle.
A58: 57 | B58: Bahrain | C58: Capital Governorate | D58: Manama | E58: Accelerator / Incubator | F58: StartUp Bahrain | G58: National startup ecosystem platform | H58: Bahrain startup community platform connecting founders, programs, partners and ecosystem contributors. | I58: StartUp Bahrain Team | J58: Partnership / ecosystem team | K58: help@startupbahrain.com | L58: contact@startupbahrain.com | N58: https://startupbahrain.com/ | O58: https://startupbahrain.com/contact | P58: A | Q58: Cohort mentoring, AI/product strategy, enterprise GTM, founder reviews and Germany/Europe–GCC market access. | R58: External Advisor / Mentor – AI, Product & Germany–GCC | National startup ecosystem platform | S58: I came across National startup ecosystem platform at StartUp Bahrain and its work around bahrain startup community platform connecting founders, programs, partners and ecosystem contributors. | T58: Use the program/functional email with a concise external mentor/advisor proposition. | U58: Functional / program email | V58: 46291 | W58: Already contacted | Y58: Already emailed in earlier batch (same address)
A59: 58 | B59: Bahrain | C59: Capital Governorate | D59: Manama | E59: Accelerator / Incubator | F59: Bahrain FinTech Bay | G59: Fintech ecosystem & acceleration | H59: Bahrain fintech hub supporting international fintechs, partnerships, acceleration and GCC/MENA expansion. | I59: Bader Sater | J59: Chief Executive Officer | K59: info@bahrainfintechbay.com | N59: https://www.bahrainfintechbay.com/team | O59: https://www.bahrainfintechbay.com/contact-us | P59: A | Q59: Cohort mentoring, AI/product strategy, enterprise GTM, founder reviews and Germany/Europe–GCC market access. | R59: External Advisor / Mentor – AI, Product & Germany–GCC | Fintech ecosystem & acceleration | S59: I came across Fintech ecosystem & acceleration at Bahrain FinTech Bay and its work around bahrain fintech hub supporting international fintechs, partnerships, acceleration and gcc/mena expansion. | T59: Write directly to the named contact using the public email and ask about contributing to the mentor/advisor network. | U59: Named contact + public email | V59: 46291 | W59: Sent | X59: 46291 | Y59: Strong enterprise/fintech/market-access mentoring angle.
A60: 59 | B60: Bahrain | C60: Capital Governorate | D60: Manama | E60: Accelerator / Incubator | F60: Bahrain FinTech Bay | G60: Acceleration Programs | H60: Bahrain FinTech Bay acceleration function supporting startup growth and innovation programs. | I60: Ameera Mohamed | J60: Manager, Acceleration Programs | K60: info@bahrainfintechbay.com | N60: https://www.bahrainfintechbay.com/team | O60: https://www.bahrainfintechbay.com/contact-us | P60: A | Q60: Cohort mentoring, AI/product strategy, enterprise GTM, founder reviews and Germany/Europe–GCC market access. | R60: External Advisor / Mentor – AI, Product & Germany–GCC | Acceleration Programs | S60: I came across Acceleration Programs at Bahrain FinTech Bay and its work around bahrain fintech bay acceleration function supporting startup growth and innovation programs. | T60: Write directly to the named contact using the public email and ask about contributing to the mentor/advisor network. | U60: Named contact + public email | V60: 46291 | W60: Skipped | Y60: Bahrain FinTech Bay covered by one email to same inbox
A61: 60 | B61: Bahrain | C61: Capital Governorate | D61: Manama | E61: Accelerator / Incubator | F61: Tenmou – Bahrain Business Angels Company | G61: MENA Angel Investors Summit / startup ecosystem | H61: Bahrain angel-investment ecosystem convening startups, investors and partners across the MENA region. | I61: Tenmou Summit Team | J61: Partnership / investor ecosystem | K61: menasummit@tenmou.me | M61: +973 3322 8028 | N61: https://tenmou.me/ | O61: https://tenmou.me/mena-angel-investors-summit-2026-2/ | P61: A | Q61: Cohort mentoring, AI/product strategy, enterprise GTM, founder reviews and Germany/Europe–GCC market access. | R61: External Advisor / Mentor – AI, Product & Germany–GCC | Tenmou – Bahrain Business Angels Company | S61: I came across MENA Angel Investors Summit / startup ecosystem at Tenmou – Bahrain Business Angels Company and its work around bahrain angel-investment ecosystem convening startups, investors and partners across the mena region. | T61: Use the program/functional email with a concise external mentor/advisor proposition. | U61: Functional / program email | V61: 46291 | W61: Sent | X61: 46291 | Y61: Current 2026 summit explicitly accepts partnership conversations.
A62: 61 | B62: Bahrain | C62: Capital Governorate | D62: Manama | E62: Accelerator / Incubator | F62: Hope Ventures | G62: Beban / venture ecosystem | H62: Bahrain venture platform supporting scalable startups through investment, acceleration and ecosystem exposure. | I62: Latifa Mohammed | J62: General Manager | N62: https://www.hopefund.bh/about-hope-ventures | O62: https://www.hopefund.bh/ | P62: B | Q62: Cohort mentoring, AI/product strategy, enterprise GTM, founder reviews and Germany/Europe–GCC market access. | R62: External Advisor / Mentor – AI, Product & Germany–GCC | Beban / venture ecosystem | S62: I came across Beban / venture ecosystem at Hope Ventures and its work around bahrain venture platform supporting scalable startups through investment, acceleration and ecosystem exposure. | T62: Use the official contact/partnership route and ask to be connected to the mentor, partnerships or incubation lead. | U62: Official route – no public email verified | V62: 46291 | W62: Skipped | Y62: No email in database
A63: 62 | B63: Bahrain | C63: Southern Governorate | D63: Sakhir | E63: Engineering / Technology University | F63: University of Bahrain | G63: Bahrain Innovation & Technology Transfer Center (BITTC) | H63: University technology transfer center helping commercialize research and facilitate startup incubation. | I63: BITTC Team | J63: Innovation & technology transfer | K63: bittc@uob.edu.bh | N63: https://www.uob.edu.bh/our-centers/bittc/ | O63: https://www.uob.edu.bh/our-centers/bittc/ | P63: A | Q63: AI/product strategy, enterprise technology, research commercialization, founder mentoring and Germany–GCC market connections. | R63: External Advisor / Mentor – AI, Product & Germany–GCC | University of Bahrain | S63: I came across Bahrain Innovation & Technology Transfer Center (BITTC) at University of Bahrain and its work around university technology transfer center helping commercialize research and facilitate startup incubation. | T63: Use the program/functional email with a concise external mentor/advisor proposition. | U63: Functional / program email | V63: 46291 | W63: Sent | X63: 46291 | Y63: Strong commercialization/advisor fit and current public email.
A64: 63 | B64: Bahrain | C64: Capital Governorate | D64: Isa Town | E64: Engineering / Technology University | F64: Bahrain Polytechnic | G64: Innovation Centre | H64: Applied university innovation ecosystem with startup/demo-day activity and an explicit mentor community. | I64: Innovation Centre Team | J64: Innovation / entrepreneurship team | N64: https://www.polytechnic.bh/research/ | O64: https://www.polytechnic.bh/startup-demo-day-2026/ | P64: A | Q64: AI/product strategy, enterprise technology, research commercialization, founder mentoring and Germany–GCC market connections. | R64: External Advisor / Mentor – AI, Product & Germany–GCC | Innovation Centre | S64: I came across Innovation Centre at Bahrain Polytechnic and its work around applied university innovation ecosystem with startup/demo-day activity and an explicit mentor community. | T64: Use the official contact/partnership route and ask to be connected to the mentor, partnerships or incubation lead. | U64: Official route – no public email verified | V64: 46291 | W64: Skipped | Y64: No email in database
A65: 64 | B65: Bahrain | C65: Capital Governorate | D65: Salmaniya | E65: Engineering / Technology University | F65: University of Technology Bahrain (UTB) | G65: Innovation & industry partnership ecosystem | H65: Technology university offering partnership opportunities spanning innovation, entrepreneurship and industry collaboration. | I65: UTB Team | J65: Partnership / innovation team | K65: info@utb.edu.bh | M65: +973 1778 7978 | N65: https://www.utb.edu.bh/ | O65: https://www.utb.edu.bh/partner-with-us/ | P65: A | Q65: AI/product strategy, enterprise technology, research commercialization, founder mentoring and Germany–GCC market connections. | R65: External Advisor / Mentor – AI, Product & Germany–GCC | University of Technology Bahrain (UTB) | S65: I came across Innovation & industry partnership ecosystem at University of Technology Bahrain (UTB) and its work around technology university offering partnership opportunities spanning innovation, entrepreneurship and industry collaboration. | T65: Use the program/functional email with a concise external mentor/advisor proposition. | U65: Functional / program email | V65: 46291 | W65: Skipped | Y65: Only a general university info inbox
A66: 65 | B66: Bahrain | C66: Capital Governorate | D66: Manama | E66: Accelerator / Incubator | F66: Brinc / Batelco | G66: Brinc Batelco IoT Hub | H66: Accelerator focused on connected hardware, IoT and technology ventures in Bahrain. | I66: Brinc Bahrain Team | J66: Accelerator team | N66: https://web.brinc.io/brinc-batelco-iot-hub/ | O66: https://web.brinc.io/brinc-batelco-iot-hub/ | P66: B | Q66: Cohort mentoring, AI/product strategy, enterprise GTM, founder reviews and Germany/Europe–GCC market access. | R66: External Advisor / Mentor – AI, Product & Germany–GCC | Brinc Batelco IoT Hub | S66: I came across Brinc Batelco IoT Hub at Brinc / Batelco and its work around accelerator focused on connected hardware, iot and technology ventures in bahrain. | T66: Use the official contact/partnership route and ask to be connected to the mentor, partnerships or incubation lead. | U66: Official route – no public email verified | V66: 46291 | W66: Skipped | Y66: No email in database

Sheet Mail Ready
A1: Country | B1: Region | C1: Category | D1: Organisation | E1: Program / Unit | F1: Contact Name | G1: Contact Role | H1: Primary Email | I1: Alternate Email | J1: Priority | K1: Suggested Subject | L1: Personalization Hook | M1: Profile / Contact URL | N1: Email Status
A2: UAE | B2: Abu Dhabi | C2: Accelerator / Incubator | D2: Hub71 | E2: Hub71 startup ecosystem | F2: Hub71 Team | G2: Ecosystem / startup team | H2: info@hub71.com | J2: A | K2: External Advisor / Mentor – AI, Product & Germany–GCC | Hub71 startup ecosystem | L2: I came across Hub71 startup ecosystem at Hub71 and its work around abu dhabi global tech ecosystem offering startup programs, market access, investor and corporate connections. | M2: https://www.hub71.com/ | N2: Already contacted
A3: UAE | B3: Abu Dhabi | C3: Accelerator / Incubator | D3: startAD – NYU Abu Dhabi | E3: startAD | F3: Ashwin Joshi | G3: Director, startAD | H3: startAD@nyu.edu | J3: A | K3: External Advisor / Mentor – AI, Product & Germany–GCC | startAD | L3: I came across startAD at startAD – NYU Abu Dhabi and its work around nyu abu dhabi-based accelerator and innovation platform connecting startups, corporates, investors and mentors. | M3: https://startad.ae/ | N3: Already contacted
A4: UAE | B4: Dubai | C4: Accelerator / Incubator | D4: Dubai Technology Entrepreneur Campus (Dtec) | E4: Dtec | F4: Dtec Team | G4: Startup / ecosystem team | H4: dtec.sales@dtec.ae | I4: community@dtec.ae | J4: A | K4: External Advisor / Mentor – AI, Product & Germany–GCC | Dtec | L4: I came across Dtec at Dubai Technology Entrepreneur Campus (Dtec) and its work around dubai silicon oasis technology startup hub offering incubation, workspace, market access and ecosystem support. | M4: https://dtec.ae/ | N4: Skipped
A5: UAE | B5: Dubai | C5: Government / Startup Ecosystem | D5: Mohammed Bin Rashid Innovation Fund (MBRIF) | E5: Innovation Accelerator | F5: MBRIF Team | G5: Innovation / accelerator team | H5: contact@mbrif.ae | I5: info@mbrinnovationfund.ae | J5: A | K5: External Mentor / Advisor Support | Innovation Accelerator | L5: I came across Innovation Accelerator at Mohammed Bin Rashid Innovation Fund (MBRIF) and its work around uae ministry of finance initiative supporting innovative companies through acceleration and growth services. | M5: https://mbrif.ae/ | N5: Sent
A6: UAE | B6: Sharjah | C6: Accelerator / Incubator | D6: Sharjah Entrepreneurship Center (Sheraa) | E6: Sheraa | F6: Sara Abdelaziz Al Nuaimi | G6: CEO | H6: info@sheraa.ae | J6: A | K6: External Advisor / Mentor – AI, Product & Germany–GCC | Sheraa | L6: I came across Sheraa at Sharjah Entrepreneurship Center (Sheraa) and its work around sharjah startup ecosystem builder supporting founders through programs, incubation, mentorship and market access. | M6: https://sheraa.ae/about-us | N6: Already contacted
A7: UAE | B7: Dubai | C7: Government / Startup Ecosystem | D7: Dubai Chamber of Digital Economy | E7: Digital Economy ecosystem | F7: Digital Economy Team | G7: Customer / ecosystem team | H7: customercare@dubaichamber.com | J7: A | K7: External Mentor / Advisor Support | Digital Economy ecosystem | L7: I came across Digital Economy ecosystem at Dubai Chamber of Digital Economy and its work around dubai chambers entity supporting digital companies, startups, market entry and ecosystem development. | M7: https://www.dubaichamber.com/ | N7: Skipped
A8: UAE | B8: Abu Dhabi | C8: Government / Startup Ecosystem | D8: Khalifa Fund for Enterprise Development | E8: Entrepreneurship support | F8: Khalifa Fund Team | G8: Entrepreneurship support team | H8: info@khalifafund.ae | J8: A | K8: External Mentor / Advisor Support | Entrepreneurship support | L8: I came across Entrepreneurship support at Khalifa Fund for Enterprise Development and its work around abu dhabi government entity supporting entrepreneurship, sme development, capability building and market access. | M8: https://www.khalifafund.ae/ | N8: Sent
A9: UAE | B9: Sharjah | C9: Government / Startup Ecosystem | D9: Sharjah SME – RUWAD | E9: Entrepreneurship support | F9: RUWAD Team | G9: SME / entrepreneurship team | H9: info@ruwad.ae | I9: cs@ruwad.ae | J9: A | K9: External Mentor / Advisor Support | Entrepreneurship support | L9: I came across Entrepreneurship support at Sharjah SME – RUWAD and its work around sharjah government sme development body supporting entrepreneurs through advisory, training and business support. | M9: https://www.ruwad.ae/ | N9: Sent
A10: UAE | B10: Dubai | C10: B-School / University Entrepreneurship | D10: University of Dubai | E10: Innovation, Entrepreneurship & Business Centre (IEBC) | F10: IEBC Team | G10: Entrepreneurship & incubation team | H10: Info.iebc@ud.ac.ae | I10: startup.support@ud.ac.ae | J10: A | K10: External Advisor / Mentor – AI, Product & Germany–GCC | University of Dubai | L10: I came across Innovation, Entrepreneurship & Business Centre (IEBC) at University of Dubai and its work around university entrepreneurship centre offering pitch competitions, workshops, mentoring, incubation and ecosystem connections. | M10: https://ud.ac.ae/entrepreneurship-and-business-centre-udiebc/ | N10: Already contacted
A11: UAE | B11: Abu Dhabi | C11: Engineering / Technology University | D11: Khalifa University | E11: Technology Management & Innovation | F11: Aysha Ali Rashed AlNuaimi | G11: Acting Director, Technology Management & Innovation | H11: aysha.alnuaimi@ku.ac.ae | I11: ip@ku.ac.ae | J11: A | K11: External Advisor / Mentor – AI, Product & Germany–GCC | Technology Management & Innovation | L11: I came across Technology Management & Innovation at Khalifa University and its work around university office responsible for research commercialization, startups, licensing and industry engagement. | M11: https://www.ku.ac.ae/research-offices/technology-management-innovation/our-team | N11: Sent
A12: UAE | B12: Abu Dhabi | C12: Engineering / Technology University | D12: Mohamed bin Zayed University of Artificial Intelligence (MBZUAI) | E12: Incubation & Entrepreneurship Center (IEC) | F12: IEC Team | G12: Incubation & Entrepreneurship Center | H12: iec@mbzuai.ac.ae | I12: info@mbzuai.ac.ae | J12: A | K12: External Advisor / Mentor – AI, Product & Germany–GCC | Mohamed bin Zayed University of Artificial Intelligence (MBZUAI) | L12: I came across Incubation & Entrepreneurship Center (IEC) at Mohamed bin Zayed University of Artificial Intelligence (MBZUAI) and its work around ai university incubation center helping founders build and scale ai startups, with mentor and ecosystem partner networks. | M12: https://mbzuai.ac.ae/innovation-partnerships/incubation-entrepreneurship-center | N12: Sent
A13: UAE | B13: Sharjah | C13: Engineering / Technology University | D13: University of Sharjah | E13: Innovation Hub | F13: Engr. Mahmoud Abu Shammeh | G13: Director, Innovation Hub | H13: abushammeh@sharjah.ac.ae | I13: mmadi@sharjah.ac.ae | J13: A | K13: External Advisor / Mentor – AI, Product & Germany–GCC | Innovation Hub | L13: I came across Innovation Hub at University of Sharjah and its work around university innovation hub supporting entrepreneurship, technology development and commercialization. | M13: https://www.sharjah.ac.ae/en/Services/Departments/Innovation-Hub | N13: Sent
A14: UAE | B14: Abu Dhabi | C14: B-School / University Entrepreneurship | D14: United Arab Emirates University (UAEU) | E14: Emirates Centre for Entrepreneurship Research | F14: Dr. Ishara Maharaj | G14: Entrepreneurship research contact | H14: ishara.maharaj@uaeu.ac.ae | I14: savagepd@uaeu.ac.ae | J14: B | K14: External Advisor / Mentor – AI, Product & Germany–GCC | United Arab Emirates University (UAEU) | L14: I came across Emirates Centre for Entrepreneurship Research at United Arab Emirates University (UAEU) and its work around university entrepreneurship research ecosystem linking entrepreneurship, education, research and enterprise development. | M14: https://www.uaeu.ac.ae/en/research/ | N14: Sent
A15: UAE | B15: Dubai | C15: Engineering / Technology University | D15: Rochester Institute of Technology Dubai (RIT Dubai) | E15: Projects & Development / entrepreneurship ecosystem | F15: Yousef Al Mannaee | G15: Projects & Development Manager | H15: yaacad@rit.edu | I15: dubai@rit.edu | J15: A | K15: External Advisor / Mentor – AI, Product & Germany–GCC | Rochester Institute of Technology Dubai (RIT Dubai) | L15: I came across Projects & Development / entrepreneurship ecosystem at Rochester Institute of Technology Dubai (RIT Dubai) and its work around technology-focused dubai campus with industry projects and entrepreneurship-oriented activities. | M15: https://www.rit.edu/dubai/directory | N15: Sent
A16: UAE | B16: Dubai | C16: B-School / University Entrepreneurship | D16: SP Jain School of Global Management | E16: Dubai Campus | F16: Amol Sawant | G16: Dubai campus contact | H16: amol.sawant@spjain.org | I16: admissions.dxb@spjain.org | J16: B | K16: External Advisor / Mentor – AI, Product & Germany–GCC | Dubai Campus | L16: I came across Dubai Campus at SP Jain School of Global Management and its work around global business school with dubai campus and entrepreneurship/business programs. | M16: https://www.spjain.org/global-campus/dubai | N16: Sent
A17: Saudi Arabia | B17: Riyadh | C17: Government / Startup Ecosystem | D17: Monsha'at – Small and Medium Enterprises General Authority | E17: Innovation Center | F17: Monsha'at Innovation Center Team | G17: Innovation Center | H17: InnovationCenters@monshaat.gov.sa | I17: Info@monshaat.gov.sa | J17: A | K17: External Mentor / Advisor Support | Innovation Center | L17: I came across Innovation Center at Monsha'at – Small and Medium Enterprises General Authority and its work around saudi government innovation centers supporting technology startups through incubation, consultations, workshops and expert guidance. | M17: https://www.monshaat.gov.sa/en/innovation_center | N17: Sent
A18: Saudi Arabia | B18: Riyadh | C18: Government / Startup Ecosystem | D18: Ministry of Communications and Information Technology (MCIT) | E18: CODE Gate | F18: CODE / MCIT Team | G18: Technology entrepreneurship team | H18: info@mcit.gov.sa | J18: A | K18: External Mentor / Advisor Support | CODE Gate | L18: I came across CODE Gate at Ministry of Communications and Information Technology (MCIT) and its work around government technology entrepreneurship platform supporting digital startups and innovation programs. | M18: https://code.mcit.gov.sa/ | N18: Skipped
A19: Saudi Arabia | B19: Riyadh | C19: Government / Startup Ecosystem | D19: Ministry of Communications and Information Technology (MCIT) | E19: Tech Founders | F19: Tech Founders Team | G19: Technology entrepreneurship program | H19: info@mcit.gov.sa | J19: B | K19: External Mentor / Advisor Support | Tech Founders | L19: I came across Tech Founders at Ministry of Communications and Information Technology (MCIT) and its work around mcit technology entrepreneurship program supporting startup founders and technology venture development. | M19: https://www.mcit.gov.sa/ | N19: Skipped
A20: Saudi Arabia | B20: Riyadh | C20: Accelerator / Incubator | D20: Mohammed bin Salman Foundation (Misk) | E20: Misk Entrepreneurship | F20: Misk Entrepreneurship Team | G20: Entrepreneurship team | H20: contact@misk.org.sa | J20: A | K20: External Advisor / Mentor – AI, Product & Germany–GCC | Misk Entrepreneurship | L20: I came across Misk Entrepreneurship at Mohammed bin Salman Foundation (Misk) and its work around entrepreneurship programs supporting young founders, venture development and ecosystem connections. | M20: https://misk.org.sa/en/ | N20: Sent
A21: Saudi Arabia | B21: Makkah Province | C21: Engineering / Technology University | D21: King Abdullah University of Science and Technology (KAUST) | E21: Entrepreneurship Center | F21: KAUST Entrepreneurship Team | G21: Entrepreneurship Center | H21: leap@kaust.edu.sa | I21: entrepreneurship@kaust.edu.sa | J21: A | K21: External Advisor / Mentor – AI, Product & Germany–GCC | Entrepreneurship Center | L21: I came across Entrepreneurship Center at King Abdullah University of Science and Technology (KAUST) and its work around kaust entrepreneurship ecosystem supporting technology founders, startup training and acceleration. | M21: https://leap.kaust.edu.sa/entrepreneurship-center.html | N21: Sent
A22: Saudi Arabia | B22: Makkah Province | C22: Accelerator / Incubator | D22: KAUST | E22: TAQADAM Accelerator | F22: TAQADAM Team | G22: Accelerator team | H22: Apply.Taqadam@kaust.edu.sa | J22: A | K22: External Advisor / Mentor – AI, Product & Germany–GCC | TAQADAM Accelerator | L22: I came across TAQADAM Accelerator at KAUST and its work around kaust startup accelerator supporting early-stage ventures with mentoring, training and ecosystem access. | M22: https://taqadam.kaust.edu.sa/ | N22: Skipped
A23: Saudi Arabia | B23: Makkah Province | C23: Accelerator / Incubator | D23: KAUST | E23: KAUST Innovation Fund | F23: KAUST Innovation Fund Team | G23: Innovation Fund | H23: KIF@kaust.edu.sa | I23: entrepreneurship@kaust.edu.sa | J23: A | K23: External Advisor / Mentor – AI, Product & Germany–GCC | KAUST Innovation Fund | L23: I came across KAUST Innovation Fund at KAUST and its work around university-linked venture fund investing in technology startups and spin-ins, including international ventures establishing activity in saudi arabia. | M23: https://www.kaust.edu.sa/ | N23: Skipped
A24: Saudi Arabia | B24: Riyadh | C24: B-School / University Entrepreneurship | D24: King Saud University | E24: Entrepreneurship Institute | F24: Dr. Khalid Alhussaini | G24: Executive Director, Entrepreneurship Institute | H24: kalhussaini@ksu.edu.sa | I24: fmalessa@ksu.edu.sa | J24: A | K24: External Advisor / Mentor – AI, Product & Germany–GCC | Entrepreneurship Institute | L24: I came across Entrepreneurship Institute at King Saud University and its work around university entrepreneurship institute supporting innovation, entrepreneurial education and venture development. | M24: https://ei.ksu.edu.sa/en/workteam_En | N24: Sent
A25: Saudi Arabia | B25: Makkah Province | C25: Engineering / Technology University | D25: King Abdulaziz University | E25: Center for Innovation & Entrepreneurship | F25: Center for Innovation & Entrepreneurship Team | G25: Center team | H25: iec@kau.edu.sa | J25: A | K25: External Advisor / Mentor – AI, Product & Germany–GCC | Center for Innovation & Entrepreneurship | L25: I came across Center for Innovation & Entrepreneurship at King Abdulaziz University and its work around university center supporting innovation, startup creation and entrepreneurship. | M25: https://kau.edu.sa/en/page/center-for-innovation-and-entrepreneurship | N25: Already contacted
A26: Saudi Arabia | B26: Eastern Province | C26: Engineering / Technology University | D26: King Fahd University of Petroleum & Minerals (KFUPM) | E26: Entrepreneurship Institute | F26: Prof. Wail A. Mousa | G26: Entrepreneurship / faculty contact | H26: wailmousa@kfupm.edu.sa | J26: B | K26: External Advisor / Mentor – AI, Product & Germany–GCC | Entrepreneurship Institute | L26: I came across Entrepreneurship Institute at King Fahd University of Petroleum & Minerals (KFUPM) and its work around technology university entrepreneurship ecosystem supporting innovation and startup development. | M26: https://faculty.kfupm.edu.sa/EE/wailmousa/ | N26: Skipped
A27: Saudi Arabia | B27: Riyadh | C27: B-School / University Entrepreneurship | D27: Alfaisal University | E27: Center for Innovation, Partnership & Community Engagement (CIPC) | F27: CIPC Team | G27: Innovation & partnerships team | H27: cipc@alfaisal.edu | J27: A | K27: External Advisor / Mentor – AI, Product & Germany–GCC | Alfaisal University | L27: I came across Center for Innovation, Partnership & Community Engagement (CIPC) at Alfaisal University and its work around university center connecting innovation, partnerships, entrepreneurship and community/industry engagement. | M27: https://cipc.alfaisal.edu/ | N27: Skipped
A28: Saudi Arabia | B28: Riyadh | C28: Accelerator / Incubator | D28: Alfaisal University | E28: Alfaisal Accelerator | F28: Alfaisal Accelerator Team | G28: Accelerator team | H28: center@alfaisal.edu | J28: A | K28: External Advisor / Mentor – AI, Product & Germany–GCC | Alfaisal Accelerator | L28: I came across Alfaisal Accelerator at Alfaisal University and its work around university accelerator supporting venture development and entrepreneurship. | M28: https://center.alfaisal.edu/accelerator | N28: Sent
A29: Saudi Arabia | B29: Riyadh | C29: B-School / University Entrepreneurship | D29: Prince Sultan University | E29: Entrepreneurship Club | F29: Entrepreneurship Club Team | G29: Entrepreneurship community | H29: epclub@psu.edu.sa | J29: C | K29: External Advisor / Mentor – AI, Product & Germany–GCC | Entrepreneurship Club | L29: I came across Entrepreneurship Club at Prince Sultan University and its work around university entrepreneurship community offering student/founder activities and business exposure. | M29: https://www.psu.edu.sa/en/resources | N29: Sent
A30: Oman | B30: Muscat | C30: Government / Startup Ecosystem | D30: Small and Medium Enterprises Development Authority (Riyada) | E30: SME & entrepreneurship ecosystem | F30: H.E. Halima Al-Zari | G30: Chairperson | H30: Doc@sme.gov.om | I30: support_dpt@sme.gov.om | J30: A | K30: External Mentor / Advisor Support | SME & entrepreneurship ecosystem | L30: I came across SME & entrepreneurship ecosystem at Small and Medium Enterprises Development Authority (Riyada) and its work around oman government authority supporting smes, entrepreneurs, incubators and entrepreneurship programs. | M30: https://sme.gov.om/en/ | N30: Sent
A31: Oman | B31: Muscat | C31: Government / Startup Ecosystem | D31: ITHCA Group | E31: Technology investment & innovation ecosystem | F31: ITHCA Team | G31: Innovation / investment ecosystem | H31: info@ithca.om | J31: A | K31: External Mentor / Advisor Support | ITHCA Group | L31: I came across Technology investment & innovation ecosystem at ITHCA Group and its work around oman technology investment group supporting ict, innovation, digital businesses and national technology development. | M31: https://ithca.om/ | N31: Sent
A32: Oman | B32: Muscat | C32: Accelerator / Incubator | D32: Oman Technology Fund (OTF) | E32: Technology investment / acceleration | F32: OTF Team | G32: Investment / accelerator team | H32: info@otf.om | J32: A | K32: External Advisor / Mentor – AI, Product & Germany–GCC | Technology investment / acceleration | L32: I came across Technology investment / acceleration at Oman Technology Fund (OTF) and its work around technology investment platform supporting innovative technology ventures and ecosystem development. | M32: https://www.otf.om/ | N32: Sent
A33: Oman | B33: Muscat | C33: Government / Startup Ecosystem | D33: Oman Startup Hub | E33: National startup ecosystem platform | F33: Oman Startup Hub Team | G33: Startup ecosystem team | H33: support@omanstartuphub.om | J33: A | K33: External Mentor / Advisor Support | National startup ecosystem platform | L33: I came across National startup ecosystem platform at Oman Startup Hub and its work around digital startup ecosystem platform connecting founders, advisors, investors and support organizations in oman. | M33: https://omanstartuphub.om/ | N33: Sent
A34: Oman | B34: Muscat | C34: Engineering / Technology University | D34: Sultan Qaboos University | E34: Innovation & Technology Transfer Centre | F34: Dr. Adil Said Ali Al-Busaidi | G34: Director, Innovation & Technology Transfer Centre | H34: abusaid@squ.edu.om | I34: innovation@squ.edu.om | J34: A | K34: External Advisor / Mentor – AI, Product & Germany–GCC | Innovation & Technology Transfer Centre | L34: I came across Innovation & Technology Transfer Centre at Sultan Qaboos University and its work around university innovation center covering incubation, mentoring, industry links, licensing, accelerators and entrepreneurship development. | M34: https://www.squ.edu.om/rc/Innovation-Technology-Transfer/About-the-Center | N34: Sent
A35: Oman | B35: Muscat | C35: Accelerator / Incubator | D35: Middle East College | E35: MEC Incubation Centre | F35: Incubation Centre Contact | G35: Incubation centre | H35: ralhatmi@mec.edu.om | J35: A | K35: External Advisor / Mentor – AI, Product & Germany–GCC | MEC Incubation Centre | L35: I came across MEC Incubation Centre at Middle East College and its work around university incubation center supporting student and startup entrepreneurship. | M35: https://mec.edu.om/en/mec-incubation-centre/ | N35: Sent
A36: Oman | B36: Al Batinah North | C36: Engineering / Technology University | D36: Sohar University | E36: Technology Transfer & Incubation Centre | F36: Tameema Al-Hinai | G36: Technology Transfer & Incubation Centre | H36: thinai@su.edu.om | I36: FSHshibli@su.edu.om | J36: A | K36: External Advisor / Mentor – AI, Product & Germany–GCC | Technology Transfer & Incubation Centre | L36: I came across Technology Transfer & Incubation Centre at Sohar University and its work around university center supporting technology transfer, commercialization, entrepreneurship and incubation. | M36: https://www.su.edu.om/knowledge-transfer-and-incubation-centre/ | N36: Sent
A37: Oman | B37: Muscat | C37: Engineering / Technology University | D37: National University of Science & Technology | E37: Incubation Centre – Money Factory | F37: Ibrahim Issa Al Balushi | G37: Head, Incubation Centre | H37: info@nu.edu.om | J37: B | K37: External Advisor / Mentor – AI, Product & Germany–GCC | Incubation Centre – Money Factory | L37: I came across Incubation Centre – Money Factory at National University of Science & Technology and its work around university incubation initiative focused on innovation, entrepreneurship and venture development. | M37: https://nu.edu.om/research/research-incubation-centers/ | N37: Skipped
A38: Oman | B38: Muscat | C38: B-School / University Entrepreneurship | D38: College of Banking and Financial Studies | E38: Innovation & entrepreneurship ecosystem | F38: CBFS Team | G38: Innovation / business education | H38: info@cbfs.edu.om | J38: B | K38: External Advisor / Mentor – AI, Product & Germany–GCC | Innovation & entrepreneurship ecosystem | L38: I came across Innovation & entrepreneurship ecosystem at College of Banking and Financial Studies and its work around oman higher-education institution focused on business, banking, finance and professional development, with innovation/entrepreneurship activity. | M38: https://cbfs.edu.om/ | N38: Skipped
A39: Oman | B39: Muscat | C39: B-School / University Entrepreneurship | D39: Muscat University | E39: Business & entrepreneurship ecosystem | F39: Muscat University Team | G39: University / business programs | H39: info@muscatuniversity.edu.om | I39: study@muscatuniversity.edu.om | J39: B | K39: External Advisor / Mentor – AI, Product & Germany–GCC | Business & entrepreneurship ecosystem | L39: I came across Business & entrepreneurship ecosystem at Muscat University and its work around private university with business, logistics and technology programs and industry engagement. | M39: https://muscatuniversity.edu.om/ | N39: Skipped
A40: Oman | B40: Ash Sharqiyah South | C40: Engineering / Technology University | D40: University of Technology and Applied Sciences (UTAS) – Sur | E40: Entrepreneurship / applied technology ecosystem | F40: UTAS Sur Team | G40: University / entrepreneurship route | H40: pro.sur@utas.edu.om | J40: C | K40: External Advisor / Mentor – AI, Product & Germany–GCC | University of Technology and Applied Sciences (UTAS) – Sur | L40: I came across Entrepreneurship / applied technology ecosystem at University of Technology and Applied Sciences (UTAS) – Sur and its work around applied-technology university branch with entrepreneurship and industry-facing academic activity. | M40: https://www.utas.edu.om/sur/ | N40: Skipped
A41: Kuwait | B41: Al Asimah | C41: Government / Startup Ecosystem | D41: National Fund for SME Development | E41: SME support, incubation & accelerator ecosystem | F41: National Fund Team | G41: SME / entrepreneurship support | H41: Info@nationalfund.gov.kw | J41: A | K41: External Mentor / Advisor Support | National Fund for SME Development | L41: I came across SME support, incubation & accelerator ecosystem at National Fund for SME Development and its work around kuwait government fund supporting smes through training, incubators, innovation centers, accelerators and support services. | M41: https://www.nationalfund.gov.kw/en/ | N41: Sent
A42: Kuwait | B42: Al Asimah | C42: Engineering / Technology University | D42: Kuwait University | E42: Department of Institutional Innovation / Kuwait University Innovation Zone | F42: KUIZ Team | G42: Institutional innovation | H42: kuiz@ku.edu.kw | J42: A | K42: External Advisor / Mentor – AI, Product & Germany–GCC | Kuwait University | L42: I came across Department of Institutional Innovation / Kuwait University Innovation Zone at Kuwait University and its work around university innovation platform supporting institutional innovation and entrepreneurship activities. | M42: https://kuiz.ku.edu.kw/ | N42: Sent
A43: Kuwait | B43: Al Ahmadi | C43: B-School / University Entrepreneurship | D43: American University of the Middle East (AUM) | E43: AI & Entrepreneurship / MBA ecosystem | F43: AUM Team | G43: AI / entrepreneurship program | H43: info@aum.edu.kw | I43: MBA.admissions@aum.edu.kw | J43: B | K43: External Advisor / Mentor – AI, Product & Germany–GCC | AI & Entrepreneurship / MBA ecosystem | L43: I came across AI & Entrepreneurship / MBA ecosystem at American University of the Middle East (AUM) and its work around university offering entrepreneurship and ai-focused executive/academic programs and business education. | M43: https://www.aum.edu.kw/ | N43: Skipped
A44: Kuwait | B44: Al Asimah | C44: B-School / University Entrepreneurship | D44: American University of Kuwait (AUK) | E44: College of Business & Economics | F44: Dr. Naeimah Alkharafi | G44: Entrepreneurship / business faculty | H44: nalkharafi@auk.edu.kw | I44: cbe@auk.edu.kw | J44: A | K44: External Advisor / Mentor – AI, Product & Germany–GCC | College of Business & Economics | L44: I came across College of Business & Economics at American University of Kuwait (AUK) and its work around business school with entrepreneurship, innovation and management teaching/research. | M44: https://www.auk.edu.kw/academics/college-of-business-economics | N44: Sent
A45: Kuwait | B45: Al Asimah | C45: Accelerator / Incubator | D45: Sirdab Lab | E45: Startup accelerator / entrepreneurship community | F45: Sirdab Lab Team | G45: Startup programs | H45: info@sirdab-lab.com | J45: A | K45: External Advisor / Mentor – AI, Product & Germany–GCC | Sirdab Lab | L45: I came across Startup accelerator / entrepreneurship community at Sirdab Lab and its work around kuwait entrepreneurship platform providing startup programs, training and ecosystem support. | M45: https://sirdab-lab.com/ | N45: Already contacted
A46: Kuwait | B46: Al Asimah | C46: Accelerator / Incubator | D46: Kuwait Innovation Center | E46: Innovation Center | F46: Mohammad AlRefaei | G46: Chief Executive Officer | H46: info@kinncenter.com | J46: A | K46: External Advisor / Mentor – AI, Product & Germany–GCC | Innovation Center | L46: I came across Innovation Center at Kuwait Innovation Center and its work around innovation platform supporting entrepreneurship, innovation programs and business development. | M46: https://www.kinncenter.com/ | N46: Sent
A47: Kuwait | B47: Al Asimah | C47: Government / Startup Ecosystem | D47: Kuwait Foundation for the Advancement of Sciences (KFAS) | E47: Innovation & Enterprise | F47: Innovation & Enterprise Team | G47: Enterprise support | H47: enterprisesupport@kfas.org.kw | J47: A | K47: External Mentor / Advisor Support | Innovation & Enterprise | L47: I came across Innovation & Enterprise at Kuwait Foundation for the Advancement of Sciences (KFAS) and its work around national science and innovation foundation supporting enterprise innovation and commercialization programs. | M47: https://www.kfas.org/ | N47: Sent
A48: Bahrain | B48: Capital Governorate | C48: Government / Startup Ecosystem | D48: Tamkeen – Labour Fund | E48: Entrepreneurship & enterprise support | F48: Tamkeen Team | G48: Enterprise support | H48: support@tamkeen.bh | I48: info@tamkeen.bh | J48: A | K48: External Mentor / Advisor Support | Entrepreneurship & enterprise support | L48: I came across Entrepreneurship & enterprise support at Tamkeen – Labour Fund and its work around bahrain public-sector institution supporting enterprise growth, skills, entrepreneurship and business development. | M48: https://www.tamkeen.bh/ | N48: Sent
A49: Bahrain | B49: Capital Governorate | C49: Government / Startup Ecosystem | D49: Bahrain Economic Development Board (Bahrain EDB) | E49: Investment & innovation ecosystem | F49: Bahrain EDB Team | G49: Investment / ecosystem team | H49: hello@bahrainedb.com | J49: A | K49: External Mentor / Advisor Support | Investment & innovation ecosystem | L49: I came across Investment & innovation ecosystem at Bahrain Economic Development Board (Bahrain EDB) and its work around bahrain investment promotion agency supporting companies, market entry and stakeholder introductions across growth sectors. | M49: https://www.bahrainedb.com/ | N49: Sent
A50: Bahrain | B50: Capital Governorate | C50: Accelerator / Incubator | D50: StartUp Bahrain | E50: National startup ecosystem platform | F50: StartUp Bahrain Team | G50: Partnership / ecosystem team | H50: help@startupbahrain.com | I50: contact@startupbahrain.com | J50: A | K50: External Advisor / Mentor – AI, Product & Germany–GCC | National startup ecosystem platform | L50: I came across National startup ecosystem platform at StartUp Bahrain and its work around bahrain startup community platform connecting founders, programs, partners and ecosystem contributors. | M50: https://startupbahrain.com/ | N50: Already contacted
A51: Bahrain | B51: Capital Governorate | C51: Accelerator / Incubator | D51: Bahrain FinTech Bay | E51: Fintech ecosystem & acceleration | F51: Bader Sater | G51: Chief Executive Officer | H51: info@bahrainfintechbay.com | J51: A | K51: External Advisor / Mentor – AI, Product & Germany–GCC | Fintech ecosystem & acceleration | L51: I came across Fintech ecosystem & acceleration at Bahrain FinTech Bay and its work around bahrain fintech hub supporting international fintechs, partnerships, acceleration and gcc/mena expansion. | M51: https://www.bahrainfintechbay.com/team | N51: Sent
A52: Bahrain | B52: Capital Governorate | C52: Accelerator / Incubator | D52: Bahrain FinTech Bay | E52: Acceleration Programs | F52: Ameera Mohamed | G52: Manager, Acceleration Programs | H52: info@bahrainfintechbay.com | J52: A | K52: External Advisor / Mentor – AI, Product & Germany–GCC | Acceleration Programs | L52: I came across Acceleration Programs at Bahrain FinTech Bay and its work around bahrain fintech bay acceleration function supporting startup growth and innovation programs. | M52: https://www.bahrainfintechbay.com/team | N52: Sent
A53: Bahrain | B53: Capital Governorate | C53: Accelerator / Incubator | D53: Tenmou – Bahrain Business Angels Company | E53: MENA Angel Investors Summit / startup ecosystem | F53: Tenmou Summit Team | G53: Partnership / investor ecosystem | H53: menasummit@tenmou.me | J53: A | K53: External Advisor / Mentor – AI, Product & Germany–GCC | Tenmou – Bahrain Business Angels Company | L53: I came across MENA Angel Investors Summit / startup ecosystem at Tenmou – Bahrain Business Angels Company and its work around bahrain angel-investment ecosystem convening startups, investors and partners across the mena region. | M53: https://tenmou.me/ | N53: Sent
A54: Bahrain | B54: Southern Governorate | C54: Engineering / Technology University | D54: University of Bahrain | E54: Bahrain Innovation & Technology Transfer Center (BITTC) | F54: BITTC Team | G54: Innovation & technology transfer | H54: bittc@uob.edu.bh | J54: A | K54: External Advisor / Mentor – AI, Product & Germany–GCC | University of Bahrain | L54: I came across Bahrain Innovation & Technology Transfer Center (BITTC) at University of Bahrain and its work around university technology transfer center helping commercialize research and facilitate startup incubation. | M54: https://www.uob.edu.bh/our-centers/bittc/ | N54: Sent
A55: Bahrain | B55: Capital Governorate | C55: Engineering / Technology University | D55: University of Technology Bahrain (UTB) | E55: Innovation & industry partnership ecosystem | F55: UTB Team | G55: Partnership / innovation team | H55: info@utb.edu.bh | J55: A | K55: External Advisor / Mentor – AI, Product & Germany–GCC | University of Technology Bahrain (UTB) | L55: I came across Innovation & industry partnership ecosystem at University of Technology Bahrain (UTB) and its work around technology university offering partnership opportunities spanning innovation, entrepreneurship and industry collaboration. | M55: https://www.utb.edu.bh/ | N55: Skipped

Sheet UAE
A1: City | B1: Category | C1: Institution / Organisation | D1: Incubator / Program / Unit | E1: Organisation Profile / Relevance | F1: Contact Name | G1: Contact Role | H1: Primary Email | I1: Alternate Email | J1: Phone | K1: Contact / Profile URL | L1: Official Source URL | M1: Priority | N1: Why Madhiyazhagan Fits | O1: Suggested Subject | P1: Best Entry Route | Q1: Contact Quality | R1: Email Status | S1: Notes
A2: Abu Dhabi | B2: Accelerator / Incubator | C2: Hub71 | D2: Hub71 startup ecosystem | E2: Abu Dhabi global tech ecosystem offering startup programs, market access, investor and corporate connections. | F2: Hub71 Team | G2: Ecosystem / startup team | H2: info@hub71.com | J2: +971 2 449 1515 | K2: https://www.hub71.com/ | L2: https://www.hub71.com/contact | M2: A | N2: Cohort mentoring, AI/product strategy, enterprise GTM, founder reviews and Germany/Europe–GCC market access. | O2: External Advisor / Mentor – AI, Product & Germany–GCC | Hub71 startup ecosystem | P2: Use the program/functional email with a concise external mentor/advisor proposition. | Q2: Functional / program email | R2: Already contacted | S2: Already emailed in earlier batch (same address)
A3: Abu Dhabi | B3: Accelerator / Incubator | C3: startAD – NYU Abu Dhabi | D3: startAD | E3: NYU Abu Dhabi-based accelerator and innovation platform connecting startups, corporates, investors and mentors. | F3: Ashwin Joshi | G3: Director, startAD | H3: startAD@nyu.edu | K3: https://startad.ae/ | L3: https://startad.ae/contact/ | M3: A | N3: Cohort mentoring, AI/product strategy, enterprise GTM, founder reviews and Germany/Europe–GCC market access. | O3: External Advisor / Mentor – AI, Product & Germany–GCC | startAD | P3: Write directly to the named contact using the public email and ask about contributing to the mentor/advisor network. | Q3: Named contact + public email | R3: Already contacted | S3: Already emailed in earlier batch (same address)
A4: Dubai | B4: Accelerator / Incubator | C4: Dubai Technology Entrepreneur Campus (Dtec) | D4: Dtec | E4: Dubai Silicon Oasis technology startup hub offering incubation, workspace, market access and ecosystem support. | F4: Dtec Team | G4: Startup / ecosystem team | H4: dtec.sales@dtec.ae | I4: community@dtec.ae | J4: +971 4 501 5000 | K4: https://dtec.ae/ | L4: https://dtec.ae/contact/ | M4: A | N4: Cohort mentoring, AI/product strategy, enterprise GTM, founder reviews and Germany/Europe–GCC market access. | O4: External Advisor / Mentor – AI, Product & Germany–GCC | Dtec | P4: Use the program/functional email with a concise external mentor/advisor proposition. | Q4: Functional / program email | R4: Skipped | S4: Dtec already emailed (dtec@dso.ae)
A5: Dubai | B5: Government / Startup Ecosystem | C5: Mohammed Bin Rashid Innovation Fund (MBRIF) | D5: Innovation Accelerator | E5: UAE Ministry of Finance initiative supporting innovative companies through acceleration and growth services. | F5: MBRIF Team | G5: Innovation / accelerator team | H5: contact@mbrif.ae | I5: info@mbrinnovationfund.ae | K5: https://mbrif.ae/ | L5: https://mbrif.ae/ar/contact-us-2/ | M5: A | N5: Founder capacity building, AI adoption, mentor programs, ecosystem partnerships and Germany/Europe–GCC market connections. | O5: External Mentor / Advisor Support | Innovation Accelerator | P5: Use the program/functional email with a concise external mentor/advisor proposition. | Q5: Functional / program email | R5: Sent | S5: Position around founder mentoring, enterprise readiness and international expansion.
A6: Sharjah | B6: Accelerator / Incubator | C6: Sharjah Entrepreneurship Center (Sheraa) | D6: Sheraa | E6: Sharjah startup ecosystem builder supporting founders through programs, incubation, mentorship and market access. | F6: Sara Abdelaziz Al Nuaimi | G6: CEO | H6: info@sheraa.ae | J6: +971 6 558 5000 | K6: https://sheraa.ae/about-us | L6: https://sheraa.ae/contact-us | M6: A | N6: Cohort mentoring, AI/product strategy, enterprise GTM, founder reviews and Germany/Europe–GCC market access. | O6: External Advisor / Mentor – AI, Product & Germany–GCC | Sheraa | P6: Write directly to the named contact using the public email and ask about contributing to the mentor/advisor network. | Q6: Named contact + public email | R6: Already contacted | S6: Already emailed in earlier batch (same address)
A7: Dubai | B7: Accelerator / Incubator | C7: DIFC Innovation Hub | D7: Innovation Hub | E7: Dubai International Financial Centre innovation ecosystem for fintech, AI, digital assets and venture growth. | F7: Mohammad Alblooshi | G7: Chief Executive Officer | K7: https://www.innovationhub.difc.ae/the-hub/about-innovation-hub | L7: https://www.innovationhub.difc.ae/ | M7: B | N7: Cohort mentoring, AI/product strategy, enterprise GTM, founder reviews and Germany/Europe–GCC market access. | O7: External Advisor / Mentor – AI, Product & Germany–GCC | Innovation Hub | P7: Use the official contact/partnership route and ask to be connected to the mentor, partnerships or incubation lead. | Q7: Official route – no public email verified | R7: Not Contacted | S7: No direct public outreach email verified; use official contact route.
A8: Dubai | B8: Government / Startup Ecosystem | C8: Dubai Future Foundation | D8: Future ecosystem / innovation programs | E8: Dubai government innovation platform running future technology, startup and ecosystem initiatives. | F8: Dubai Future Foundation Team | G8: Partnership / innovation team | J8: +971 4 516 6565 | K8: https://www.dubaifuture.ae/ | L8: https://www.dubaifuture.ae/reach-us/ | M8: B | N8: Founder capacity building, AI adoption, mentor programs, ecosystem partnerships and Germany/Europe–GCC market connections. | O8: External Mentor / Advisor Support | Future ecosystem / innovation programs | P8: Use the official contact/partnership route and ask to be connected to the mentor, partnerships or incubation lead. | Q8: Official route – no public email verified | R8: Not Contacted | S8: Use partnership enquiry route; do not use technical-support email for outreach.
A9: Dubai | B9: Government / Startup Ecosystem | C9: Dubai Chamber of Digital Economy | D9: Digital Economy ecosystem | E9: Dubai Chambers entity supporting digital companies, startups, market entry and ecosystem development. | F9: Digital Economy Team | G9: Customer / ecosystem team | H9: customercare@dubaichamber.com | J9: 800 CHAMBER (242 6237) | K9: https://www.dubaichamber.com/ | L9: https://myhub.dubaichamber.com/en/web/dubai-chamber-of-digital-economy/home | M9: A | N9: Founder capacity building, AI adoption, mentor programs, ecosystem partnerships and Germany/Europe–GCC market connections. | O9: External Mentor / Advisor Support | Digital Economy ecosystem | P9: Use the program/functional email with a concise external mentor/advisor proposition. | Q9: Functional / program email | R9: Skipped | S9: Only a customer care inbox
A10: Abu Dhabi | B10: Government / Startup Ecosystem | C10: Khalifa Fund for Enterprise Development | D10: Entrepreneurship support | E10: Abu Dhabi government entity supporting entrepreneurship, SME development, capability building and market access. | F10: Khalifa Fund Team | G10: Entrepreneurship support team | H10: info@khalifafund.ae | J10: +971 2 696 0000 | K10: https://www.khalifafund.ae/ | L10: https://www.khalifafund.ae/contact/ | M10: A | N10: Founder capacity building, AI adoption, mentor programs, ecosystem partnerships and Germany/Europe–GCC market connections. | O10: External Mentor / Advisor Support | Entrepreneurship support | P10: Use the program/functional email with a concise external mentor/advisor proposition. | Q10: Functional / program email | R10: Sent | S10: Offer founder mentoring, AI adoption and Germany/Europe connections.
A11: Sharjah | B11: Government / Startup Ecosystem | C11: Sharjah SME – RUWAD | D11: Entrepreneurship support | E11: Sharjah government SME development body supporting entrepreneurs through advisory, training and business support. | F11: RUWAD Team | G11: SME / entrepreneurship team | H11: info@ruwad.ae | I11: cs@ruwad.ae | J11: +971 6 512 2555 | K11: https://www.ruwad.ae/ | L11: https://www.ruwad.ae/ | M11: A | N11: Founder capacity building, AI adoption, mentor programs, ecosystem partnerships and Germany/Europe–GCC market connections. | O11: External Mentor / Advisor Support | Entrepreneurship support | P11: Use the program/functional email with a concise external mentor/advisor proposition. | Q11: Functional / program email | R11: Sent | S11: Good route for mentor/advisor contribution to SME founders.
A12: Dubai | B12: B-School / University Entrepreneurship | C12: University of Dubai | D12: Innovation, Entrepreneurship & Business Centre (IEBC) | E12: University entrepreneurship centre offering pitch competitions, workshops, mentoring, incubation and ecosystem connections. | F12: IEBC Team | G12: Entrepreneurship & incubation team | H12: Info.iebc@ud.ac.ae | I12: startup.support@ud.ac.ae | J12: +971 4 556 6800 | K12: https://ud.ac.ae/entrepreneurship-and-business-centre-udiebc/ | L12: https://ud.ac.ae/entrepreneurship-and-business-centre-udiebc/ | M12: A | N12: Startup mentoring, business models, GTM, enterprise readiness, entrepreneurship education and Germany–GCC connections. | O12: External Advisor / Mentor – AI, Product & Germany–GCC | University of Dubai | P12: Use the program/functional email with a concise external mentor/advisor proposition. | Q12: Functional / program email | R12: Already contacted | S12: Already emailed in earlier batch (same address)
A13: Abu Dhabi | B13: Engineering / Technology University | C13: Khalifa University | D13: Technology Management & Innovation | E13: University office responsible for research commercialization, startups, licensing and industry engagement. | F13: Aysha Ali Rashed AlNuaimi | G13: Acting Director, Technology Management & Innovation | H13: aysha.alnuaimi@ku.ac.ae | I13: ip@ku.ac.ae | K13: https://www.ku.ac.ae/research-offices/technology-management-innovation/our-team | L13: https://www.ku.ac.ae/research-offices/technology-management-innovation | M13: A | N13: AI/product strategy, enterprise technology, research commercialization, founder mentoring and Germany–GCC market connections. | O13: External Advisor / Mentor – AI, Product & Germany–GCC | Technology Management & Innovation | P13: Write directly to the named contact using the public email and ask about contributing to the mentor/advisor network. | Q13: Named contact + public email | R13: Sent | S13: Direct named decision-maker and strong commercialization fit.
A14: Abu Dhabi | B14: Engineering / Technology University | C14: Mohamed bin Zayed University of Artificial Intelligence (MBZUAI) | D14: Incubation & Entrepreneurship Center (IEC) | E14: AI university incubation center helping founders build and scale AI startups, with mentor and ecosystem partner networks. | F14: IEC Team | G14: Incubation & Entrepreneurship Center | H14: iec@mbzuai.ac.ae | I14: info@mbzuai.ac.ae | J14: +971 2 811 3333 | K14: https://mbzuai.ac.ae/innovation-partnerships/incubation-entrepreneurship-center | L14: https://mbzuai.ac.ae/about-us/contact-mbzuai | M14: A | N14: AI/product strategy, enterprise technology, research commercialization, founder mentoring and Germany–GCC market connections. | O14: External Advisor / Mentor – AI, Product & Germany–GCC | Mohamed bin Zayed University of Artificial Intelligence (MBZUAI) | P14: Use the program/functional email with a concise external mentor/advisor proposition. | Q14: Functional / program email | R14: Sent | S14: Very strong AI/startup mentoring alignment.
A15: Sharjah | B15: Engineering / Technology University | C15: University of Sharjah | D15: Innovation Hub | E15: University innovation hub supporting entrepreneurship, technology development and commercialization. | F15: Engr. Mahmoud Abu Shammeh | G15: Director, Innovation Hub | H15: abushammeh@sharjah.ac.ae | I15: mmadi@sharjah.ac.ae | K15: https://www.sharjah.ac.ae/en/Services/Departments/Innovation-Hub | L15: https://www.sharjah.ac.ae/en/Services/Departments/Innovation-Hub | M15: A | N15: AI/product strategy, enterprise technology, research commercialization, founder mentoring and Germany–GCC market connections. | O15: External Advisor / Mentor – AI, Product & Germany–GCC | Innovation Hub | P15: Write directly to the named contact using the public email and ask about contributing to the mentor/advisor network. | Q15: Named contact + public email | R15: Sent | S15: Named director; strong innovation/commercialization target.
A16: Al Ain | B16: B-School / University Entrepreneurship | C16: United Arab Emirates University (UAEU) | D16: Emirates Centre for Entrepreneurship Research | E16: University entrepreneurship research ecosystem linking entrepreneurship, education, research and enterprise development. | F16: Dr. Ishara Maharaj | G16: Entrepreneurship research contact | H16: ishara.maharaj@uaeu.ac.ae | I16: savagepd@uaeu.ac.ae | K16: https://www.uaeu.ac.ae/en/research/ | L16: https://www.uaeu.ac.ae/en/research/research-booklet-uaeu-2024.pdf | M16: B | N16: Startup mentoring, business models, GTM, enterprise readiness, entrepreneurship education and Germany–GCC connections. | O16: External Advisor / Mentor – AI, Product & Germany–GCC | United Arab Emirates University (UAEU) | P16: Write directly to the named contact using the public email and ask about contributing to the mentor/advisor network. | Q16: Named contact + public email | R16: Sent | S16: Good for entrepreneurship teaching, research and mentor collaboration.
A17: Dubai | B17: Engineering / Technology University | C17: Rochester Institute of Technology Dubai (RIT Dubai) | D17: Projects & Development / entrepreneurship ecosystem | E17: Technology-focused Dubai campus with industry projects and entrepreneurship-oriented activities. | F17: Yousef Al Mannaee | G17: Projects & Development Manager | H17: yaacad@rit.edu | I17: dubai@rit.edu | J17: +971 4 371 2000 | K17: https://www.rit.edu/dubai/directory | L17: https://www.rit.edu/dubai/ | M17: A | N17: AI/product strategy, enterprise technology, research commercialization, founder mentoring and Germany–GCC market connections. | O17: External Advisor / Mentor – AI, Product & Germany–GCC | Rochester Institute of Technology Dubai (RIT Dubai) | P17: Write directly to the named contact using the public email and ask about contributing to the mentor/advisor network. | Q17: Named contact + public email | R17: Sent | S17: Direct contact plus technology and industry-project fit.
A18: Dubai | B18: B-School / University Entrepreneurship | C18: SP Jain School of Global Management | D18: Dubai Campus | E18: Global business school with Dubai campus and entrepreneurship/business programs. | F18: Amol Sawant | G18: Dubai campus contact | H18: amol.sawant@spjain.org | I18: admissions.dxb@spjain.org | K18: https://www.spjain.org/global-campus/dubai | L18: https://www.spjain.ae/contact-us | M18: B | N18: Startup mentoring, business models, GTM, enterprise readiness, entrepreneurship education and Germany–GCC connections. | O18: External Advisor / Mentor – AI, Product & Germany–GCC | Dubai Campus | P18: Write directly to the named contact using the public email and ask about contributing to the mentor/advisor network. | Q18: Named contact + public email | R18: Sent | S18: Pitch mentor/guest advisor role around AI, product, startup execution and Europe connections.
A19: Dubai | B19: B-School / University Entrepreneurship | C19: Zayed University | D19: Innovation & Entrepreneurship Center | E19: University center supporting innovation, entrepreneurship education and engagement with ecosystem partners. | F19: Innovation & Entrepreneurship Center Team | G19: University entrepreneurship team | K19: https://www.zu.ac.ae/main/en/ie-center/index | L19: https://www.zu.ac.ae/main/en/ie-center/index | M19: B | N19: Startup mentoring, business models, GTM, enterprise readiness, entrepreneurship education and Germany–GCC connections. | O19: External Advisor / Mentor – AI, Product & Germany–GCC | Innovation & Entrepreneurship Center | P19: Use the official contact/partnership route and ask to be connected to the mentor, partnerships or incubation lead. | Q19: Official route – no public email verified | R19: Not Contacted | S19: Use center contact route; public direct email not verified.
A20: Sharjah | B20: B-School / University Entrepreneurship | C20: American University of Sharjah | D20: Department of Management, Strategy & Entrepreneurship | E20: Business-school department covering entrepreneurship, strategy and management with industry-facing academic activity. | F20: Dr. Virginia Bodolica | G20: Department leadership | K20: https://www.aus.edu/sba/department-of-management-strategy-entrepreneurship | L20: https://www.aus.edu/sba/department-of-management-strategy-entrepreneurship | M20: C | N20: Startup mentoring, business models, GTM, enterprise readiness, entrepreneurship education and Germany–GCC connections. | O20: External Advisor / Mentor – AI, Product & Germany–GCC | American University of Sharjah | P20: Use the official contact/partnership route and ask to be connected to the mentor, partnerships or incubation lead. | Q20: Official route – no public email verified | R20: Not Contacted | S20: No direct public email verified in current page; use university directory/contact route.

Sheet Saudi Arabia
A1: City | B1: Category | C1: Institution / Organisation | D1: Incubator / Program / Unit | E1: Organisation Profile / Relevance | F1: Contact Name | G1: Contact Role | H1: Primary Email | I1: Alternate Email | J1: Phone | K1: Contact / Profile URL | L1: Official Source URL | M1: Priority | N1: Why Madhiyazhagan Fits | O1: Suggested Subject | P1: Best Entry Route | Q1: Contact Quality | R1: Email Status | S1: Notes
A2: Riyadh | B2: Government / Startup Ecosystem | C2: Monsha'at – Small and Medium Enterprises General Authority | D2: Innovation Center | E2: Saudi government innovation centers supporting technology startups through incubation, consultations, workshops and expert guidance. | F2: Monsha'at Innovation Center Team | G2: Innovation Center | H2: InnovationCenters@monshaat.gov.sa | I2: Info@monshaat.gov.sa | J2: 8003018888 | K2: https://www.monshaat.gov.sa/en/innovation_center | L2: https://www.monshaat.gov.sa/en/support | M2: A | N2: Founder capacity building, AI adoption, mentor programs, ecosystem partnerships and Germany/Europe–GCC market connections. | O2: External Mentor / Advisor Support | Innovation Center | P2: Use the program/functional email with a concise external mentor/advisor proposition. | Q2: Functional / program email | R2: Sent | S2: Explicit expert consultations make this a strong external-mentor target.
A3: Riyadh | B3: Government / Startup Ecosystem | C3: Ministry of Communications and Information Technology (MCIT) | D3: CODE Gate | E3: Government technology entrepreneurship platform supporting digital startups and innovation programs. | F3: CODE / MCIT Team | G3: Technology entrepreneurship team | H3: info@mcit.gov.sa | J3: 011 814 4444 | K3: https://code.mcit.gov.sa/ | L3: https://my.gov.sa/en/services/2477063 | M3: A | N3: Founder capacity building, AI adoption, mentor programs, ecosystem partnerships and Germany/Europe–GCC market connections. | O3: External Mentor / Advisor Support | CODE Gate | P3: Use the program/functional email with a concise external mentor/advisor proposition. | Q3: Functional / program email | R3: Skipped | S3: Only a general ministry inbox
A4: Riyadh | B4: Government / Startup Ecosystem | C4: Ministry of Communications and Information Technology (MCIT) | D4: Tech Founders | E4: MCIT technology entrepreneurship program supporting startup founders and technology venture development. | F4: Tech Founders Team | G4: Technology entrepreneurship program | H4: info@mcit.gov.sa | J4: 011 814 4444 | K4: https://www.mcit.gov.sa/ | L4: https://my.gov.sa/en/services/2422923 | M4: B | N4: Founder capacity building, AI adoption, mentor programs, ecosystem partnerships and Germany/Europe–GCC market connections. | O4: External Mentor / Advisor Support | Tech Founders | P4: Use the program/functional email with a concise external mentor/advisor proposition. | Q4: Functional / program email | R4: Skipped | S4: Only a general ministry inbox
A5: Riyadh | B5: Accelerator / Incubator | C5: Mohammed bin Salman Foundation (Misk) | D5: Misk Entrepreneurship | E5: Entrepreneurship programs supporting young founders, venture development and ecosystem connections. | F5: Misk Entrepreneurship Team | G5: Entrepreneurship team | H5: contact@misk.org.sa | K5: https://misk.org.sa/en/ | L5: https://misk.org.sa/en/ask-misk-en/ | M5: A | N5: Cohort mentoring, AI/product strategy, enterprise GTM, founder reviews and Germany/Europe–GCC market access. | O5: External Advisor / Mentor – AI, Product & Germany–GCC | Misk Entrepreneurship | P5: Use the program/functional email with a concise external mentor/advisor proposition. | Q5: Functional / program email | R5: Sent | S5: Pitch practical founder mentoring and international-market sessions.
A6: Thuwal | B6: Engineering / Technology University | C6: King Abdullah University of Science and Technology (KAUST) | D6: Entrepreneurship Center | E6: KAUST entrepreneurship ecosystem supporting technology founders, startup training and acceleration. | F6: KAUST Entrepreneurship Team | G6: Entrepreneurship Center | H6: leap@kaust.edu.sa | I6: entrepreneurship@kaust.edu.sa | K6: https://leap.kaust.edu.sa/entrepreneurship-center.html | L6: https://www.kaust.edu.sa/ | M6: A | N6: AI/product strategy, enterprise technology, research commercialization, founder mentoring and Germany–GCC market connections. | O6: External Advisor / Mentor – AI, Product & Germany–GCC | Entrepreneurship Center | P6: Use the program/functional email with a concise external mentor/advisor proposition. | Q6: Functional / program email | R6: Sent | S6: Deep-tech commercialization and international-market fit.
A7: Thuwal | B7: Accelerator / Incubator | C7: KAUST | D7: TAQADAM Accelerator | E7: KAUST startup accelerator supporting early-stage ventures with mentoring, training and ecosystem access. | F7: TAQADAM Team | G7: Accelerator team | H7: Apply.Taqadam@kaust.edu.sa | K7: https://taqadam.kaust.edu.sa/ | L7: https://taqadam.kaust.edu.sa/ | M7: A | N7: Cohort mentoring, AI/product strategy, enterprise GTM, founder reviews and Germany/Europe–GCC market access. | O7: External Advisor / Mentor – AI, Product & Germany–GCC | TAQADAM Accelerator | P7: Use the program/functional email with a concise external mentor/advisor proposition. | Q7: Functional / program email | R7: Skipped | S7: KAUST covered via Entrepreneurship Center email
A8: Thuwal | B8: Accelerator / Incubator | C8: KAUST | D8: KAUST Innovation Fund | E8: University-linked venture fund investing in technology startups and spin-ins, including international ventures establishing activity in Saudi Arabia. | F8: KAUST Innovation Fund Team | G8: Innovation Fund | H8: KIF@kaust.edu.sa | I8: entrepreneurship@kaust.edu.sa | K8: https://www.kaust.edu.sa/ | L8: https://www.kaust.edu.sa/en/news/how-kaust-is-enabling-the-in-kingdom-entrepreneurs-of-tomorrow | M8: A | N8: Cohort mentoring, AI/product strategy, enterprise GTM, founder reviews and Germany/Europe–GCC market access. | O8: External Advisor / Mentor – AI, Product & Germany–GCC | KAUST Innovation Fund | P8: Use the program/functional email with a concise external mentor/advisor proposition. | Q8: Functional / program email | R8: Skipped | S8: KAUST covered via Entrepreneurship Center email
A9: Riyadh | B9: B-School / University Entrepreneurship | C9: King Saud University | D9: Entrepreneurship Institute | E9: University entrepreneurship institute supporting innovation, entrepreneurial education and venture development. | F9: Dr. Khalid Alhussaini | G9: Executive Director, Entrepreneurship Institute | H9: kalhussaini@ksu.edu.sa | I9: fmalessa@ksu.edu.sa | J9: 011 806 2212 | K9: https://ei.ksu.edu.sa/en/workteam_En | L9: https://ei.ksu.edu.sa/en/workteam_En | M9: A | N9: Startup mentoring, business models, GTM, enterprise readiness, entrepreneurship education and Germany–GCC connections. | O9: External Advisor / Mentor – AI, Product & Germany–GCC | Entrepreneurship Institute | P9: Write directly to the named contact using the public email and ask about contributing to the mentor/advisor network. | Q9: Named contact + public email | R9: Sent | S9: Direct named leadership.
A10: Jeddah | B10: Engineering / Technology University | C10: King Abdulaziz University | D10: Center for Innovation & Entrepreneurship | E10: University center supporting innovation, startup creation and entrepreneurship. | F10: Center for Innovation & Entrepreneurship Team | G10: Center team | H10: iec@kau.edu.sa | K10: https://kau.edu.sa/en/page/center-for-innovation-and-entrepreneurship | L10: https://kau.edu.sa/en/page/center-for-innovation-and-entrepreneurship | M10: A | N10: AI/product strategy, enterprise technology, research commercialization, founder mentoring and Germany–GCC market connections. | O10: External Advisor / Mentor – AI, Product & Germany–GCC | Center for Innovation & Entrepreneurship | P10: Use the program/functional email with a concise external mentor/advisor proposition. | Q10: Functional / program email | R10: Already contacted | S10: Already emailed in earlier batch (same address)
A11: Dhahran | B11: Engineering / Technology University | C11: King Fahd University of Petroleum & Minerals (KFUPM) | D11: Entrepreneurship Institute | E11: Technology university entrepreneurship ecosystem supporting innovation and startup development. | F11: Prof. Wail A. Mousa | G11: Entrepreneurship / faculty contact | H11: wailmousa@kfupm.edu.sa | K11: https://faculty.kfupm.edu.sa/EE/wailmousa/ | L11: https://www.kfupm.edu.sa/ | M11: B | N11: AI/product strategy, enterprise technology, research commercialization, founder mentoring and Germany–GCC market connections. | O11: External Advisor / Mentor – AI, Product & Germany–GCC | Entrepreneurship Institute | P11: Write directly to the named contact using the public email and ask about contributing to the mentor/advisor network. | Q11: Named contact + public email | R11: Skipped | S11: KFUPM already emailed (ei@kfupm.edu.sa)
A12: Riyadh | B12: B-School / University Entrepreneurship | C12: Alfaisal University | D12: Center for Innovation, Partnership & Community Engagement (CIPC) | E12: University center connecting innovation, partnerships, entrepreneurship and community/industry engagement. | F12: CIPC Team | G12: Innovation & partnerships team | H12: cipc@alfaisal.edu | J12: +966 11 215 7792 | K12: https://cipc.alfaisal.edu/ | L12: https://cipc.alfaisal.edu/contact-us | M12: A | N12: Startup mentoring, business models, GTM, enterprise readiness, entrepreneurship education and Germany–GCC connections. | O12: External Advisor / Mentor – AI, Product & Germany–GCC | Alfaisal University | P12: Use the program/functional email with a concise external mentor/advisor proposition. | Q12: Functional / program email | R12: Skipped | S12: Alfaisal covered via Accelerator email (CIPC in cc)
A13: Riyadh | B13: Accelerator / Incubator | C13: Alfaisal University | D13: Alfaisal Accelerator | E13: University accelerator supporting venture development and entrepreneurship. | F13: Alfaisal Accelerator Team | G13: Accelerator team | H13: center@alfaisal.edu | J13: +966 11 215 7967 | K13: https://center.alfaisal.edu/accelerator | L13: https://center.alfaisal.edu/accelerator | M13: A | N13: Cohort mentoring, AI/product strategy, enterprise GTM, founder reviews and Germany/Europe–GCC market access. | O13: External Advisor / Mentor – AI, Product & Germany–GCC | Alfaisal Accelerator | P13: Use the program/functional email with a concise external mentor/advisor proposition. | Q13: Functional / program email | R13: Sent | S13: Direct accelerator route.
A14: Jeddah | B14: B-School / University Entrepreneurship | C14: Effat University | D14: Business Innovation & Entrepreneurship Research Center | E14: University research center focused on business innovation and entrepreneurship. | F14: Center Team | G14: Business innovation / entrepreneurship center | K14: https://www.effatuniversity.edu.sa/English/Research/Research-Centers/Business-Innovation-and-Entrepreneurship/Pages/default.aspx | L14: https://www.effatuniversity.edu.sa/English/Research/Research-Centers/Business-Innovation-and-Entrepreneurship/Pages/default.aspx | M14: B | N14: Startup mentoring, business models, GTM, enterprise readiness, entrepreneurship education and Germany–GCC connections. | O14: External Advisor / Mentor – AI, Product & Germany–GCC | Effat University | P14: Use the official contact/partnership route and ask to be connected to the mentor, partnerships or incubation lead. | Q14: Official route – no public email verified | R14: Not Contacted | S14: Use official university enquiry route; direct public center email not verified.
A15: Riyadh | B15: B-School / University Entrepreneurship | C15: Prince Sultan University | D15: Entrepreneurship Club | E15: University entrepreneurship community offering student/founder activities and business exposure. | F15: Entrepreneurship Club Team | G15: Entrepreneurship community | H15: epclub@psu.edu.sa | K15: https://www.psu.edu.sa/en/resources | L15: https://www.psu.edu.sa/en/resources | M15: C | N15: Startup mentoring, business models, GTM, enterprise readiness, entrepreneurship education and Germany–GCC connections. | O15: External Advisor / Mentor – AI, Product & Germany–GCC | Entrepreneurship Club | P15: Use the program/functional email with a concise external mentor/advisor proposition. | Q15: Functional / program email | R15: Sent | S15: Student-facing route; use for workshops/guest mentoring rather than formal board ask.
A16: Riyadh | B16: Accelerator / Incubator | C16: stc | D16: inspireU | E16: Corporate accelerator supporting digital/technology startups with business support, mentoring and market opportunities. | F16: inspireU Team | G16: Corporate accelerator | K16: https://www.stc.com/en/inspire-u/apply-now.html | L16: https://www.stc.com/en/inspire-u/apply-now.html | M16: B | N16: Cohort mentoring, AI/product strategy, enterprise GTM, founder reviews and Germany/Europe–GCC market access. | O16: External Advisor / Mentor – AI, Product & Germany–GCC | inspireU | P16: Use the official contact/partnership route and ask to be connected to the mentor, partnerships or incubation lead. | Q16: Official route – no public email verified | R16: Not Contacted | S16: High-value target; no current official outreach email verified, use program contact/application route.
A17: Riyadh | B17: Accelerator / Incubator | C17: The Garage | D17: Startup / deep-tech innovation hub | E17: Riyadh startup hub supporting technology founders, accelerators, venture programs and innovation community activity. | F17: The Garage Team | G17: Startup ecosystem team | K17: https://thegarage.sa/ | L17: https://erp.thegarage.sa/contactus | M17: B | N17: Cohort mentoring, AI/product strategy, enterprise GTM, founder reviews and Germany/Europe–GCC market access. | O17: External Advisor / Mentor – AI, Product & Germany–GCC | Startup / deep-tech innovation hub | P17: Use the official contact/partnership route and ask to be connected to the mentor, partnerships or incubation lead. | Q17: Official route – no public email verified | R17: Not Contacted | S17: High-value but current public email not reliably verified; use official contact form.

Sheet Oman
A1: City | B1: Category | C1: Institution / Organisation | D1: Incubator / Program / Unit | E1: Organisation Profile / Relevance | F1: Contact Name | G1: Contact Role | H1: Primary Email | I1: Alternate Email | J1: Phone | K1: Contact / Profile URL | L1: Official Source URL | M1: Priority | N1: Why Madhiyazhagan Fits | O1: Suggested Subject | P1: Best Entry Route | Q1: Contact Quality | R1: Email Status | S1: Notes
A2: Muscat | B2: Government / Startup Ecosystem | C2: Small and Medium Enterprises Development Authority (Riyada) | D2: SME & entrepreneurship ecosystem | E2: Oman government authority supporting SMEs, entrepreneurs, incubators and entrepreneurship programs. | F2: H.E. Halima Al-Zari | G2: Chairperson | H2: Doc@sme.gov.om | I2: support_dpt@sme.gov.om | J2: +968 2202 2222 | K2: https://sme.gov.om/en/ | L2: https://sme.gov.om/en/contact-us/ | M2: A | N2: Founder capacity building, AI adoption, mentor programs, ecosystem partnerships and Germany/Europe–GCC market connections. | O2: External Mentor / Advisor Support | SME & entrepreneurship ecosystem | P2: Write directly to the named contact using the public email and ask about contributing to the mentor/advisor network. | Q2: Named contact + public email | R2: Sent | S2: Government-level ecosystem target; use concise partnership/mentor proposition.
A3: Muscat | B3: Government / Startup Ecosystem | C3: ITHCA Group | D3: Technology investment & innovation ecosystem | E3: Oman technology investment group supporting ICT, innovation, digital businesses and national technology development. | F3: ITHCA Team | G3: Innovation / investment ecosystem | H3: info@ithca.om | J3: +968 2231 0500 | K3: https://ithca.om/ | L3: https://ithca.om/contact/ | M3: A | N3: Founder capacity building, AI adoption, mentor programs, ecosystem partnerships and Germany/Europe–GCC market connections. | O3: External Mentor / Advisor Support | ITHCA Group | P3: Use the program/functional email with a concise external mentor/advisor proposition. | Q3: Functional / program email | R3: Sent | S3: Strong enterprise-tech and international ecosystem fit.
A4: Muscat | B4: Accelerator / Incubator | C4: Oman Technology Fund (OTF) | D4: Technology investment / acceleration | E4: Technology investment platform supporting innovative technology ventures and ecosystem development. | F4: OTF Team | G4: Investment / accelerator team | H4: info@otf.om | J4: +968 2417 2717 | K4: https://www.otf.om/ | L4: https://www.otf.om/__trashed-3/contact/ | M4: A | N4: Cohort mentoring, AI/product strategy, enterprise GTM, founder reviews and Germany/Europe–GCC market access. | O4: External Advisor / Mentor – AI, Product & Germany–GCC | Technology investment / acceleration | P4: Use the program/functional email with a concise external mentor/advisor proposition. | Q4: Functional / program email | R4: Sent | S4: Pitch startup reviews, AI/product mentoring and international-market support.
A5: Muscat | B5: Government / Startup Ecosystem | C5: Oman Startup Hub | D5: National startup ecosystem platform | E5: Digital startup ecosystem platform connecting founders, advisors, investors and support organizations in Oman. | F5: Oman Startup Hub Team | G5: Startup ecosystem team | H5: support@omanstartuphub.om | K5: https://omanstartuphub.om/ | L5: https://omanstartuphub.om/contact-us | M5: A | N5: Founder capacity building, AI adoption, mentor programs, ecosystem partnerships and Germany/Europe–GCC market connections. | O5: External Mentor / Advisor Support | National startup ecosystem platform | P5: Use the program/functional email with a concise external mentor/advisor proposition. | Q5: Functional / program email | R5: Sent | S5: Advisor network makes this directly aligned with your objective.
A6: Muscat | B6: Engineering / Technology University | C6: Sultan Qaboos University | D6: Innovation & Technology Transfer Centre | E6: University innovation center covering incubation, mentoring, industry links, licensing, accelerators and entrepreneurship development. | F6: Dr. Adil Said Ali Al-Busaidi | G6: Director, Innovation & Technology Transfer Centre | H6: abusaid@squ.edu.om | I6: innovation@squ.edu.om | J6: +968 2414 6125 | K6: https://www.squ.edu.om/rc/Innovation-Technology-Transfer/About-the-Center | L6: https://innovation.squ.edu.om/contact-us | M6: A | N6: AI/product strategy, enterprise technology, research commercialization, founder mentoring and Germany–GCC market connections. | O6: External Advisor / Mentor – AI, Product & Germany–GCC | Innovation & Technology Transfer Centre | P6: Write directly to the named contact using the public email and ask about contributing to the mentor/advisor network. | Q6: Named contact + public email | R6: Sent | S6: Excellent direct named contact and strong advisor fit.
A7: Muscat | B7: Accelerator / Incubator | C7: Middle East College | D7: MEC Incubation Centre | E7: University incubation center supporting student and startup entrepreneurship. | F7: Incubation Centre Contact | G7: Incubation centre | H7: ralhatmi@mec.edu.om | K7: https://mec.edu.om/en/mec-incubation-centre/ | L7: https://mec.edu.om/en/mec-incubation-centre/ | M7: A | N7: Cohort mentoring, AI/product strategy, enterprise GTM, founder reviews and Germany/Europe–GCC market access. | O7: External Advisor / Mentor – AI, Product & Germany–GCC | MEC Incubation Centre | P7: Use the program/functional email with a concise external mentor/advisor proposition. | Q7: Functional / program email | R7: Sent | S7: Good mentor/workshop target.
A8: Sohar | B8: Engineering / Technology University | C8: Sohar University | D8: Technology Transfer & Incubation Centre | E8: University center supporting technology transfer, commercialization, entrepreneurship and incubation. | F8: Tameema Al-Hinai | G8: Technology Transfer & Incubation Centre | H8: thinai@su.edu.om | I8: FSHshibli@su.edu.om | K8: https://www.su.edu.om/knowledge-transfer-and-incubation-centre/ | L8: https://www.su.edu.om/knowledge-transfer-and-incubation-centre/ | M8: A | N8: AI/product strategy, enterprise technology, research commercialization, founder mentoring and Germany–GCC market connections. | O8: External Advisor / Mentor – AI, Product & Germany–GCC | Technology Transfer & Incubation Centre | P8: Write directly to the named contact using the public email and ask about contributing to the mentor/advisor network. | Q8: Named contact + public email | R8: Sent | S8: Direct contact; good commercialization and mentoring angle.
A9: Muscat | B9: Engineering / Technology University | C9: National University of Science & Technology | D9: Incubation Centre – Money Factory | E9: University incubation initiative focused on innovation, entrepreneurship and venture development. | F9: Ibrahim Issa Al Balushi | G9: Head, Incubation Centre | H9: info@nu.edu.om | K9: https://nu.edu.om/research/research-incubation-centers/ | L9: https://nu.edu.om/research/research-incubation-centers/ | M9: B | N9: AI/product strategy, enterprise technology, research commercialization, founder mentoring and Germany–GCC market connections. | O9: External Advisor / Mentor – AI, Product & Germany–GCC | Incubation Centre – Money Factory | P9: Write directly to the named contact using the public email and ask about contributing to the mentor/advisor network. | Q9: Named contact + public email | R9: Skipped | S9: NU Oman already emailed; only general info@ inbox
A10: Muscat | B10: B-School / University Entrepreneurship | C10: College of Banking and Financial Studies | D10: Innovation & entrepreneurship ecosystem | E10: Oman higher-education institution focused on business, banking, finance and professional development, with innovation/entrepreneurship activity. | F10: CBFS Team | G10: Innovation / business education | H10: info@cbfs.edu.om | J10: +968 2452 8888 | K10: https://cbfs.edu.om/ | L10: https://cbfs.edu.om/contact-us/ | M10: B | N10: Startup mentoring, business models, GTM, enterprise readiness, entrepreneurship education and Germany–GCC connections. | O10: External Advisor / Mentor – AI, Product & Germany–GCC | Innovation & entrepreneurship ecosystem | P10: Use the program/functional email with a concise external mentor/advisor proposition. | Q10: Functional / program email | R10: Skipped | S10: Only a general college info inbox
A11: Muscat | B11: B-School / University Entrepreneurship | C11: Muscat University | D11: Business & entrepreneurship ecosystem | E11: Private university with business, logistics and technology programs and industry engagement. | F11: Muscat University Team | G11: University / business programs | H11: info@muscatuniversity.edu.om | I11: study@muscatuniversity.edu.om | K11: https://muscatuniversity.edu.om/ | L11: https://muscatuniversity.edu.om/contact-us/ | M11: B | N11: Startup mentoring, business models, GTM, enterprise readiness, entrepreneurship education and Germany–GCC connections. | O11: External Advisor / Mentor – AI, Product & Germany–GCC | Business & entrepreneurship ecosystem | P11: Use the program/functional email with a concise external mentor/advisor proposition. | Q11: Functional / program email | R11: Skipped | S11: Only general university info/admissions inboxes
A12: Sur | B12: Engineering / Technology University | C12: University of Technology and Applied Sciences (UTAS) – Sur | D12: Entrepreneurship / applied technology ecosystem | E12: Applied-technology university branch with entrepreneurship and industry-facing academic activity. | F12: UTAS Sur Team | G12: University / entrepreneurship route | H12: pro.sur@utas.edu.om | K12: https://www.utas.edu.om/sur/ | L12: https://www.utas.edu.om/sur/ | M12: C | N12: AI/product strategy, enterprise technology, research commercialization, founder mentoring and Germany–GCC market connections. | O12: External Advisor / Mentor – AI, Product & Germany–GCC | University of Technology and Applied Sciences (UTAS) – Sur | P12: Use the program/functional email with a concise external mentor/advisor proposition. | Q12: Functional / program email | R12: Skipped | S12: Only a public relations inbox

Sheet Kuwait
A1: City | B1: Category | C1: Institution / Organisation | D1: Incubator / Program / Unit | E1: Organisation Profile / Relevance | F1: Contact Name | G1: Contact Role | H1: Primary Email | I1: Alternate Email | J1: Phone | K1: Contact / Profile URL | L1: Official Source URL | M1: Priority | N1: Why Madhiyazhagan Fits | O1: Suggested Subject | P1: Best Entry Route | Q1: Contact Quality | R1: Email Status | S1: Notes
A2: Kuwait City | B2: Government / Startup Ecosystem | C2: National Fund for SME Development | D2: SME support, incubation & accelerator ecosystem | E2: Kuwait government fund supporting SMEs through training, incubators, innovation centers, accelerators and support services. | F2: National Fund Team | G2: SME / entrepreneurship support | H2: Info@nationalfund.gov.kw | J2: 136 | K2: https://www.nationalfund.gov.kw/en/ | L2: https://www.nationalfund.gov.kw/en/about-us/our-services/support-services-center/ | M2: A | N2: Founder capacity building, AI adoption, mentor programs, ecosystem partnerships and Germany/Europe–GCC market connections. | O2: External Mentor / Advisor Support | National Fund for SME Development | P2: Use the program/functional email with a concise external mentor/advisor proposition. | Q2: Functional / program email | R2: Sent | S2: Top government ecosystem target.
A3: Kuwait City | B3: Engineering / Technology University | C3: Kuwait University | D3: Department of Institutional Innovation / Kuwait University Innovation Zone | E3: University innovation platform supporting institutional innovation and entrepreneurship activities. | F3: KUIZ Team | G3: Institutional innovation | H3: kuiz@ku.edu.kw | J3: 24982858 / 24983448 | K3: https://kuiz.ku.edu.kw/ | L3: https://kuiz.ku.edu.kw/contact-us | M3: A | N3: AI/product strategy, enterprise technology, research commercialization, founder mentoring and Germany–GCC market connections. | O3: External Advisor / Mentor – AI, Product & Germany–GCC | Kuwait University | P3: Use the program/functional email with a concise external mentor/advisor proposition. | Q3: Functional / program email | R3: Sent | S3: Strong university innovation route.
A4: Mubarak Al-Abdullah | B4: B-School / University Entrepreneurship | C4: Gulf University for Science and Technology (GUST) | D4: Startup Lab | E4: University startup lab supporting entrepreneurship, innovation and student venture activity. | F4: GUST Startup Lab Team | G4: Startup / entrepreneurship lab | K4: https://www.gust.edu.kw/sdg/sdg9 | L4: https://www.gust.edu.kw/sdg/sdg4/4-3/4-3-1 | M4: B | N4: Startup mentoring, business models, GTM, enterprise readiness, entrepreneurship education and Germany–GCC connections. | O4: External Advisor / Mentor – AI, Product & Germany–GCC | Startup Lab | P4: Use the official contact/partnership route and ask to be connected to the mentor, partnerships or incubation lead. | Q4: Official route – no public email verified | R4: Not Contacted | S4: Public direct Startup Lab email not verified; use GUST contact route.
A5: Egaila | B5: B-School / University Entrepreneurship | C5: American University of the Middle East (AUM) | D5: AI & Entrepreneurship / MBA ecosystem | E5: University offering entrepreneurship and AI-focused executive/academic programs and business education. | F5: AUM Team | G5: AI / entrepreneurship program | H5: info@aum.edu.kw | I5: MBA.admissions@aum.edu.kw | J5: +965 2225 1400 | K5: https://www.aum.edu.kw/ | L5: https://www.aum.edu.kw/english/about-aum/international-relations/aum---uc-berkeley-certification-program-in-ai-and-entrepreneurship | M5: B | N5: Startup mentoring, business models, GTM, enterprise readiness, entrepreneurship education and Germany–GCC connections. | O5: External Advisor / Mentor – AI, Product & Germany–GCC | AI & Entrepreneurship / MBA ecosystem | P5: Use the program/functional email with a concise external mentor/advisor proposition. | Q5: Functional / program email | R5: Skipped | S5: Only general info/admissions inboxes
A6: Salmiya | B6: B-School / University Entrepreneurship | C6: American University of Kuwait (AUK) | D6: College of Business & Economics | E6: Business school with entrepreneurship, innovation and management teaching/research. | F6: Dr. Naeimah Alkharafi | G6: Entrepreneurship / business faculty | H6: nalkharafi@auk.edu.kw | I6: cbe@auk.edu.kw | K6: https://www.auk.edu.kw/academics/college-of-business-economics | L6: https://www.auk.edu.kw/academics/college-of-business-economics | M6: A | N6: Startup mentoring, business models, GTM, enterprise readiness, entrepreneurship education and Germany–GCC connections. | O6: External Advisor / Mentor – AI, Product & Germany–GCC | College of Business & Economics | P6: Write directly to the named contact using the public email and ask about contributing to the mentor/advisor network. | Q6: Named contact + public email | R6: Sent | S6: Named faculty route; good mentor/guest speaker entry.
A7: Kuwait City | B7: Accelerator / Incubator | C7: Sirdab Lab | D7: Startup accelerator / entrepreneurship community | E7: Kuwait entrepreneurship platform providing startup programs, training and ecosystem support. | F7: Sirdab Lab Team | G7: Startup programs | H7: info@sirdab-lab.com | J7: +965 9776 8939 | K7: https://sirdab-lab.com/ | L7: https://sirdab-lab.com/ | M7: A | N7: Cohort mentoring, AI/product strategy, enterprise GTM, founder reviews and Germany/Europe–GCC market access. | O7: External Advisor / Mentor – AI, Product & Germany–GCC | Sirdab Lab | P7: Use the program/functional email with a concise external mentor/advisor proposition. | Q7: Functional / program email | R7: Already contacted | S7: Already emailed in earlier batch (same address)
A8: Kuwait City | B8: Accelerator / Incubator | C8: Kuwait Innovation Center | D8: Innovation Center | E8: Innovation platform supporting entrepreneurship, innovation programs and business development. | F8: Mohammad AlRefaei | G8: Chief Executive Officer | H8: info@kinncenter.com | J8: +965 9409 0194 | K8: https://www.kinncenter.com/ | L8: https://www.kinncenter.com/contactus | M8: A | N8: Cohort mentoring, AI/product strategy, enterprise GTM, founder reviews and Germany/Europe–GCC market access. | O8: External Advisor / Mentor – AI, Product & Germany–GCC | Innovation Center | P8: Write directly to the named contact using the public email and ask about contributing to the mentor/advisor network. | Q8: Named contact + public email | R8: Sent | S8: Named CEO with functional email.
A9: Kuwait City | B9: Government / Startup Ecosystem | C9: Kuwait Foundation for the Advancement of Sciences (KFAS) | D9: Innovation & Enterprise | E9: National science and innovation foundation supporting enterprise innovation and commercialization programs. | F9: Innovation & Enterprise Team | G9: Enterprise support | H9: enterprisesupport@kfas.org.kw | K9: https://www.kfas.org/ | L9: https://app.kfas.org.kw/coFunding%20Support%20Form/Form1.aspx | M9: A | N9: Founder capacity building, AI adoption, mentor programs, ecosystem partnerships and Germany/Europe–GCC market connections. | O9: External Mentor / Advisor Support | Innovation & Enterprise | P9: Use the program/functional email with a concise external mentor/advisor proposition. | Q9: Functional / program email | R9: Sent | S9: Strong innovation/commercialization and corporate ecosystem target.

Sheet Bahrain
A1: City | B1: Category | C1: Institution / Organisation | D1: Incubator / Program / Unit | E1: Organisation Profile / Relevance | F1: Contact Name | G1: Contact Role | H1: Primary Email | I1: Alternate Email | J1: Phone | K1: Contact / Profile URL | L1: Official Source URL | M1: Priority | N1: Why Madhiyazhagan Fits | O1: Suggested Subject | P1: Best Entry Route | Q1: Contact Quality | R1: Email Status | S1: Notes
A2: Manama | B2: Government / Startup Ecosystem | C2: Tamkeen – Labour Fund | D2: Entrepreneurship & enterprise support | E2: Bahrain public-sector institution supporting enterprise growth, skills, entrepreneurship and business development. | F2: Tamkeen Team | G2: Enterprise support | H2: support@tamkeen.bh | I2: info@tamkeen.bh | J2: +973 1738 3333 | K2: https://www.tamkeen.bh/ | L2: https://www.tamkeen.bh/ | M2: A | N2: Founder capacity building, AI adoption, mentor programs, ecosystem partnerships and Germany/Europe–GCC market connections. | O2: External Mentor / Advisor Support | Entrepreneurship & enterprise support | P2: Use the program/functional email with a concise external mentor/advisor proposition. | Q2: Functional / program email | R2: Sent | S2: Top public ecosystem route; pitch mentor capacity building and international connections.
A3: Manama | B3: Government / Startup Ecosystem | C3: Bahrain Economic Development Board (Bahrain EDB) | D3: Investment & innovation ecosystem | E3: Bahrain investment promotion agency supporting companies, market entry and stakeholder introductions across growth sectors. | F3: Bahrain EDB Team | G3: Investment / ecosystem team | H3: hello@bahrainedb.com | J3: +973 1758 9999 | K3: https://www.bahrainedb.com/ | L3: https://www.bahrainedb.com/contact-us | M3: A | N3: Founder capacity building, AI adoption, mentor programs, ecosystem partnerships and Germany/Europe–GCC market connections. | O3: External Mentor / Advisor Support | Investment & innovation ecosystem | P3: Use the program/functional email with a concise external mentor/advisor proposition. | Q3: Functional / program email | R3: Sent | S3: Berlin/Germany base creates a strong international ecosystem angle.
A4: Manama | B4: Accelerator / Incubator | C4: StartUp Bahrain | D4: National startup ecosystem platform | E4: Bahrain startup community platform connecting founders, programs, partners and ecosystem contributors. | F4: StartUp Bahrain Team | G4: Partnership / ecosystem team | H4: help@startupbahrain.com | I4: contact@startupbahrain.com | K4: https://startupbahrain.com/ | L4: https://startupbahrain.com/contact | M4: A | N4: Cohort mentoring, AI/product strategy, enterprise GTM, founder reviews and Germany/Europe–GCC market access. | O4: External Advisor / Mentor – AI, Product & Germany–GCC | National startup ecosystem platform | P4: Use the program/functional email with a concise external mentor/advisor proposition. | Q4: Functional / program email | R4: Already contacted | S4: Already emailed in earlier batch (same address)
A5: Manama | B5: Accelerator / Incubator | C5: Bahrain FinTech Bay | D5: Fintech ecosystem & acceleration | E5: Bahrain fintech hub supporting international fintechs, partnerships, acceleration and GCC/MENA expansion. | F5: Bader Sater | G5: Chief Executive Officer | H5: info@bahrainfintechbay.com | K5: https://www.bahrainfintechbay.com/team | L5: https://www.bahrainfintechbay.com/contact-us | M5: A | N5: Cohort mentoring, AI/product strategy, enterprise GTM, founder reviews and Germany/Europe–GCC market access. | O5: External Advisor / Mentor – AI, Product & Germany–GCC | Fintech ecosystem & acceleration | P5: Write directly to the named contact using the public email and ask about contributing to the mentor/advisor network. | Q5: Named contact + public email | R5: Sent | S5: Strong enterprise/fintech/market-access mentoring angle.
A6: Manama | B6: Accelerator / Incubator | C6: Bahrain FinTech Bay | D6: Acceleration Programs | E6: Bahrain FinTech Bay acceleration function supporting startup growth and innovation programs. | F6: Ameera Mohamed | G6: Manager, Acceleration Programs | H6: info@bahrainfintechbay.com | K6: https://www.bahrainfintechbay.com/team | L6: https://www.bahrainfintechbay.com/contact-us | M6: A | N6: Cohort mentoring, AI/product strategy, enterprise GTM, founder reviews and Germany/Europe–GCC market access. | O6: External Advisor / Mentor – AI, Product & Germany–GCC | Acceleration Programs | P6: Write directly to the named contact using the public email and ask about contributing to the mentor/advisor network. | Q6: Named contact + public email | R6: Sent | S6: More direct operational contact angle for mentor programs.
A7: Manama | B7: Accelerator / Incubator | C7: Tenmou – Bahrain Business Angels Company | D7: MENA Angel Investors Summit / startup ecosystem | E7: Bahrain angel-investment ecosystem convening startups, investors and partners across the MENA region. | F7: Tenmou Summit Team | G7: Partnership / investor ecosystem | H7: menasummit@tenmou.me | J7: +973 3322 8028 | K7: https://tenmou.me/ | L7: https://tenmou.me/mena-angel-investors-summit-2026-2/ | M7: A | N7: Cohort mentoring, AI/product strategy, enterprise GTM, founder reviews and Germany/Europe–GCC market access. | O7: External Advisor / Mentor – AI, Product & Germany–GCC | Tenmou – Bahrain Business Angels Company | P7: Use the program/functional email with a concise external mentor/advisor proposition. | Q7: Functional / program email | R7: Sent | S7: Current 2026 summit explicitly accepts partnership conversations.
A8: Manama | B8: Accelerator / Incubator | C8: Hope Ventures | D8: Beban / venture ecosystem | E8: Bahrain venture platform supporting scalable startups through investment, acceleration and ecosystem exposure. | F8: Latifa Mohammed | G8: General Manager | K8: https://www.hopefund.bh/about-hope-ventures | L8: https://www.hopefund.bh/ | M8: B | N8: Cohort mentoring, AI/product strategy, enterprise GTM, founder reviews and Germany/Europe–GCC market access. | O8: External Advisor / Mentor – AI, Product & Germany–GCC | Beban / venture ecosystem | P8: Use the official contact/partnership route and ask to be connected to the mentor, partnerships or incubation lead. | Q8: Official route – no public email verified | R8: Not Contacted | S8: High-value target; no suitable public outreach email verified, use official contact route.
A9: Sakhir | B9: Engineering / Technology University | C9: University of Bahrain | D9: Bahrain Innovation & Technology Transfer Center (BITTC) | E9: University technology transfer center helping commercialize research and facilitate startup incubation. | F9: BITTC Team | G9: Innovation & technology transfer | H9: bittc@uob.edu.bh | K9: https://www.uob.edu.bh/our-centers/bittc/ | L9: https://www.uob.edu.bh/our-centers/bittc/ | M9: A | N9: AI/product strategy, enterprise technology, research commercialization, founder mentoring and Germany–GCC market connections. | O9: External Advisor / Mentor – AI, Product & Germany–GCC | University of Bahrain | P9: Use the program/functional email with a concise external mentor/advisor proposition. | Q9: Functional / program email | R9: Sent | S9: Strong commercialization/advisor fit and current public email.
A10: Isa Town | B10: Engineering / Technology University | C10: Bahrain Polytechnic | D10: Innovation Centre | E10: Applied university innovation ecosystem with startup/demo-day activity and an explicit mentor community. | F10: Innovation Centre Team | G10: Innovation / entrepreneurship team | K10: https://www.polytechnic.bh/research/ | L10: https://www.polytechnic.bh/startup-demo-day-2026/ | M10: A | N10: AI/product strategy, enterprise technology, research commercialization, founder mentoring and Germany–GCC market connections. | O10: External Advisor / Mentor – AI, Product & Germany–GCC | Innovation Centre | P10: Use the official contact/partnership route and ask to be connected to the mentor, partnerships or incubation lead. | Q10: Official route – no public email verified | R10: Not Contacted | S10: Excellent target because mentor participation is explicitly part of the ecosystem; use official contact route.
A11: Salmaniya | B11: Engineering / Technology University | C11: University of Technology Bahrain (UTB) | D11: Innovation & industry partnership ecosystem | E11: Technology university offering partnership opportunities spanning innovation, entrepreneurship and industry collaboration. | F11: UTB Team | G11: Partnership / innovation team | H11: info@utb.edu.bh | J11: +973 1778 7978 | K11: https://www.utb.edu.bh/ | L11: https://www.utb.edu.bh/partner-with-us/ | M11: A | N11: AI/product strategy, enterprise technology, research commercialization, founder mentoring and Germany–GCC market connections. | O11: External Advisor / Mentor – AI, Product & Germany–GCC | University of Technology Bahrain (UTB) | P11: Use the program/functional email with a concise external mentor/advisor proposition. | Q11: Functional / program email | R11: Skipped | S11: Only a general university info inbox
A12: Manama | B12: Accelerator / Incubator | C12: Brinc / Batelco | D12: Brinc Batelco IoT Hub | E12: Accelerator focused on connected hardware, IoT and technology ventures in Bahrain. | F12: Brinc Bahrain Team | G12: Accelerator team | K12: https://web.brinc.io/brinc-batelco-iot-hub/ | L12: https://web.brinc.io/brinc-batelco-iot-hub/ | M12: B | N12: Cohort mentoring, AI/product strategy, enterprise GTM, founder reviews and Germany/Europe–GCC market access. | O12: External Advisor / Mentor – AI, Product & Germany–GCC | Brinc Batelco IoT Hub | P12: Use the official contact/partnership route and ask to be connected to the mentor, partnerships or incubation lead. | Q12: Official route – no public email verified | R12: Not Contacted | S12: Strong technology mentor fit; current public direct email not verified.

Sheet Email Template
A1: Gulf External Advisor / Mentor Email – Core Template
A3: Field | B3: Recommended content
A4: Subject | B4: External Advisor / Mentor – [Program / Organisation]
A5: Greeting | B5: Dear [Name],
A6: Personalized opening | B6: I came across [specific program/initiative] and wanted to explore whether I could contribute as an external advisor or mentor.
A7: Who you are | B7: I’m Madhiyazhagan Ramamoorthy, based in Berlin, with 16+ years of experience across India, the UAE and Germany in technology delivery, AI, digital transformation and product execution.
A8: Relevant contribution | B8: Alongside my professional work, I mentor founders and contribute to startup and university initiatives. I could support founders around [pick 2–3: AI/product strategy, enterprise readiness, GTM, commercialization, founder mentoring, Germany/Europe market access].
A9: Gulf angle | B9: For GCC targets, use your previous UAE experience and current Berlin base only when relevant; do not overload the email with biography.
A10: CTA | B10: Would you be open to a short introductory conversation to see whether this could be useful for your founders or current programs?
A11: Close | B11: Best regards, Madhiyazhagan Ramamoorthy Berlin, Germany LinkedIn: linkedin.com/in/madhi-pm-scrum-qa/
A12: Length rule | B12: Aim for 90–140 words. The first 1–2 sentences should be institution-specific.
A13: Approach rule | B13: Ask to contribute as advisor/mentor/mentor-panel member/ecosystem partner — not for a job.
